{"__type__":"cc.JsonAsset","_name":"CFGTripleMap1010043","json":{"MapId":"1010043","MapData":"{\"height\":9,\"infinite\":false,\"layers\":[{\"data\":[1,1,1,1,1,1,1,1,1,1,1,1,1,1,1,1,1,1,1,1,1,1,1,1,1,1,1,1,1,1,1,1,1,1,1,1,1,1,1,1,1,1,1,1,1,1,1,1,1,1,1,1,1,1,0,0,0,0,0,0,0,0,0,0,1,1,1,0,1,1,1,0,0,1,1,1,0,1,1,1,0],\"height\":9,\"name\":\"Cells\",\"opacity\":1,\"type\":\"tilelayer\",\"visible\":true,\"width\":9,\"x\":0,\"y\":0},{\"draworder\":\"topdown\",\"name\":\"Cells\",\"objects\":[],\"opacity\":1,\"properties\":{\"dropType\":\"default\"},\"propertytypes\":{\"dropType\":\"string\"},\"type\":\"objectgroup\",\"visible\":true,\"x\":0,\"y\":0},{\"data\":[0,0,0,0,0,0,0,0,0,0,0,0,0,0,0,0,0,0,0,0,0,0,0,0,0,0,0,0,0,0,0,0,0,0,0,0,0,0,0,0,0,0,0,0,0,0,0,0,0,0,0,0,0,0,0,0,0,0,0,0,0,0,0,0,0,0,0,0,0,0,0,0,0,0,0,0,0,0,0,0,0],\"height\":9,\"name\":\"Conveyers\",\"opacity\":1,\"type\":\"tilelayer\",\"visible\":true,\"width\":9,\"x\":0,\"y\":0},{\"draworder\":\"topdown\",\"name\":\"Conveyers\",\"objects\":[],\"opacity\":1,\"type\":\"objectgroup\",\"visible\":true,\"x\":0,\"y\":0},{\"data\":[0,0,0,0,0,0,0,0,0,0,0,0,0,0,0,0,0,0,0,0,0,0,0,0,0,0,0,0,0,0,0,0,0,0,0,0,0,0,0,0,0,0,0,0,0,0,0,0,0,0,0,0,0,0,0,0,0,0,0,0,0,0,0,0,54,54,54,0,55,55,55,0,0,0,0,0,0,0,0,0,0],\"height\":9,\"name\":\"Floors\",\"opacity\":1,\"type\":\"tilelayer\",\"visible\":true,\"width\":9,\"x\":0,\"y\":0},{\"data\":[0,0,0,0,0,0,0,0,0,0,0,0,0,0,0,0,0,0,0,0,0,0,0,0,0,0,0,0,0,0,0,0,0,0,0,0,0,0,0,0,0,0,0,0,0,0,0,0,0,0,0,0,0,0,0,0,0,0,0,0,0,0,0,0,0,0,0,0,0,0,0,0,0,0,0,0,0,0,0,0,0],\"height\":9,\"name\":\"Jam\",\"opacity\":1,\"type\":\"tilelayer\",\"visible\":true,\"width\":9,\"x\":0,\"y\":0},{\"data\":[182,182,182,182,182,182,182,182,182,182,182,182,182,182,182,182,182,182,182,182,182,182,182,182,182,182,182,182,182,182,182,182,182,182,182,182,182,182,182,182,182,182,182,182,182,182,182,182,182,182,182,182,182,182,0,0,0,0,0,0,0,0,0,0,0,0,0,0,0,0,0,0,0,182,182,182,0,182,182,182,0],\"height\":9,\"name\":\"Items\",\"opacity\":1,\"type\":\"tilelayer\",\"visible\":true,\"width\":9,\"x\":0,\"y\":0},{\"draworder\":\"topdown\",\"name\":\"Items\",\"objects\":[],\"opacity\":1,\"type\":\"objectgroup\",\"visible\":true,\"x\":0,\"y\":0},{\"data\":[232,0,0,0,230,0,0,0,232,232,0,0,0,230,0,0,0,232,232,0,0,0,230,0,0,0,232,232,0,0,0,230,0,0,0,232,232,0,0,0,230,0,0,0,232,232,230,230,230,230,230,230,230,232,0,0,0,0,0,0,0,0,0,0,0,0,0,0,0,0,0,0,0,232,232,232,0,232,232,232,0],\"height\":9,\"name\":\"Parasites\",\"opacity\":1,\"type\":\"tilelayer\",\"visible\":true,\"width\":9,\"x\":0,\"y\":0},{\"data\":[0,0,0,0,0,0,0,0,0,0,0,0,0,0,0,0,0,0,0,0,0,0,0,0,0,0,0,0,0,0,0,0,0,0,0,0,0,0,0,0,0,0,0,0,0,0,0,0,0,0,0,0,0,0,0,0,0,0,0,0,0,0,0,0,0,0,0,0,0,0,0,0,0,0,0,0,0,0,0,0,0],\"height\":9,\"name\":\"Marks\",\"opacity\":1,\"type\":\"tilelayer\",\"visible\":true,\"width\":9,\"x\":0,\"y\":0},{\"draworder\":\"topdown\",\"name\":\"Marks\",\"objects\":[{\"gid\":218,\"height\":100,\"id\":375,\"name\":\"\",\"properties\":{\"postal\":\"{1,1}\"},\"propertytypes\":{\"postal\":\"string\"},\"rotation\":0,\"type\":\"\",\"visible\":true,\"width\":100,\"x\":100,\"y\":600},{\"gid\":218,\"height\":100,\"id\":376,\"name\":\"\",\"properties\":{\"postal\":\"{2,1}\"},\"propertytypes\":{\"postal\":\"string\"},\"rotation\":0,\"type\":\"\",\"visible\":true,\"width\":100,\"x\":200,\"y\":600},{\"gid\":218,\"height\":100,\"id\":377,\"name\":\"\",\"properties\":{\"postal\":\"{3,1}\"},\"propertytypes\":{\"postal\":\"string\"},\"rotation\":0,\"type\":\"\",\"visible\":true,\"width\":100,\"x\":300,\"y\":600},{\"gid\":218,\"height\":100,\"id\":378,\"name\":\"\",\"properties\":{\"postal\":\"{5,1}\"},\"propertytypes\":{\"postal\":\"string\"},\"rotation\":0,\"type\":\"\",\"visible\":true,\"width\":100,\"x\":500,\"y\":600},{\"gid\":218,\"height\":100,\"id\":379,\"name\":\"\",\"properties\":{\"postal\":\"{6,1}\"},\"propertytypes\":{\"postal\":\"string\"},\"rotation\":0,\"type\":\"\",\"visible\":true,\"width\":100,\"x\":600,\"y\":600},{\"gid\":218,\"height\":100,\"id\":380,\"name\":\"\",\"properties\":{\"postal\":\"{7,1}\"},\"propertytypes\":{\"postal\":\"string\"},\"rotation\":0,\"type\":\"\",\"visible\":true,\"width\":100,\"x\":700,\"y\":600},{\"gid\":219,\"height\":100,\"id\":381,\"name\":\"\",\"rotation\":0,\"type\":\"\",\"visible\":true,\"width\":100,\"x\":100,\"y\":800},{\"gid\":219,\"height\":100,\"id\":382,\"name\":\"\",\"rotation\":0,\"type\":\"\",\"visible\":true,\"width\":100,\"x\":200,\"y\":800},{\"gid\":219,\"height\":100,\"id\":383,\"name\":\"\",\"rotation\":0,\"type\":\"\",\"visible\":true,\"width\":100,\"x\":300,\"y\":800},{\"gid\":219,\"height\":100,\"id\":384,\"name\":\"\",\"rotation\":0,\"type\":\"\",\"visible\":true,\"width\":100,\"x\":500,\"y\":800},{\"gid\":219,\"height\":100,\"id\":385,\"name\":\"\",\"rotation\":0,\"type\":\"\",\"visible\":true,\"width\":100,\"x\":600,\"y\":800},{\"gid\":219,\"height\":100,\"id\":386,\"name\":\"\",\"rotation\":0,\"type\":\"\",\"visible\":true,\"width\":100,\"x\":700,\"y\":800}],\"opacity\":1,\"type\":\"objectgroup\",\"visible\":true,\"x\":0,\"y\":0}],\"nextobjectid\":393,\"orientation\":\"orthogonal\",\"renderorder\":\"left-up\",\"tiledversion\":\"1.1.4\",\"tileheight\":100,\"tilesets\":[{\"firstgid\":1,\"source\":\"../TiledMaps/Cells.json\"},{\"firstgid\":25,\"source\":\"../TiledMaps/Conveyers.json\"},{\"firstgid\":49,\"source\":\"../TiledMaps/Floors.json\"},{\"firstgid\":85,\"source\":\"../TiledMaps/Items.json\"},{\"firstgid\":205,\"source\":\"../TiledMaps/Jam.json\"},{\"firstgid\":217,\"source\":\"../TiledMaps/Marks.json\"},{\"firstgid\":229,\"source\":\"../TiledMaps/Parasite.json\"}],\"tilewidth\":100,\"type\":\"map\",\"version\":1,\"width\":9}"}}