[{"__type__":"cc.SceneAsset","_name":"MatchScene","scene":{"__id__":1},"asyncLoadAssets":null},{"__type__":"cc.Scene","_name":"New Node","_children":[{"__id__":2}],"_active":false,"_anchorPoint":{"__type__":"cc.Vec2"},"_trs":{"__type__":"TypedArray","ctor":"Float64Array","array":[0,0,0,0,0,0,1,0.2789826320726173,0.2789826320726173,1]},"_zIndex":0,"autoReleaseAssets":false},{"__type__":"cc.Node","_name":"Canvas","_parent":{"__id__":1},"_children":[{"__id__":3},{"__id__":4},{"__id__":12},{"__id__":181}],"_components":[{"__type__":"cc.Canvas","node":{"__id__":2},"_designResolution":{"__type__":"cc.Size","width":720,"height":1280}},{"__type__":"966dbqyP51Ch4+/u9o4NkVZ","node":{"__id__":2},"bgTop":{"__id__":11},"cancelGearLayer":{"__id__":85},"backgroundMask":{"__id__":86},"swallowTouchLayer":{"__id__":181},"gridFrame":{"__id__":87},"levelLabel":{"__id__":81},"targetBar":{"__id__":84},"supplyBar":{"__id__":75},"stepBar":{"__id__":20},"scoreBar":{"__id__":37},"gearBar":{"__id__":180},"pauseButton":{"__id__":96}},{"__type__":"cc.Animation","node":{"__id__":2},"_clips":[{"__uuid__":"5fObqjut1BTrM6x1vuQOEW"},{"__uuid__":"d7y7GGE7tH2au3RJUMNHEB"}]},{"__type__":"cc.Widget","node":{"__id__":2},"_alignFlags":45}],"_contentSize":{"__type__":"cc.Size","width":720,"height":1280},"_trs":{"__type__":"TypedArray","ctor":"Float64Array","array":[360,640,0,0,0,0,1,1,1,1]},"_zIndex":0,"_id":"0fw/cBqC9KJqKt2SPYxyXP"},{"__type__":"cc.Node","_name":"Main Camera","_parent":{"__id__":2},"_components":[{"__type__":"cc.Camera","node":{"__id__":3},"_clearFlags":7,"_depth":-1}],"_trs":{"__type__":"TypedArray","ctor":"Float64Array","array":[0,0,0,0,0,0,1,1,1,1]},"_zIndex":0},{"__type__":"cc.Node","_name":"backgroundView","_parent":{"__id__":2},"_children":[{"__id__":5},{"__id__":6},{"__id__":7},{"__id__":8},{"__id__":9},{"__id__":10},{"__id__":11},{"__type__":"cc.Node","_name":"petRoot","_parent":{"__id__":4},"_trs":{"__type__":"TypedArray","ctor":"Float64Array","array":[0,370,0,0,0,0,1,0.7,0.7,1]},"_zIndex":0}],"_components":[{"__type__":"cc.Widget","node":{"__id__":4},"alignMode":0,"_alignFlags":45}],"_contentSize":{"__type__":"cc.Size","width":720,"height":1280},"_trs":{"__type__":"TypedArray","ctor":"Float64Array","array":[0,0,0,0,0,0,1,1,1,1]},"_zIndex":0},{"__type__":"cc.Node","_name":"match_background_center","_parent":{"__id__":4},"_components":[{"__type__":"cc.Sprite","node":{"__id__":5},"_spriteFrame":{"__uuid__":"23YayEr1BBtZKn1zS/A8SH"},"_type":1,"_sizeMode":0}],"_contentSize":{"__type__":"cc.Size","width":965,"height":1560},"_anchorPoint":{"__type__":"cc.Vec2","x":0.5,"y":0.4983247434291584},"_trs":{"__type__":"TypedArray","ctor":"Float64Array","array":[0,0,0,0,0,0,1,1,1,1]},"_zIndex":0},{"__type__":"cc.Node","_name":"match_background_lb","_parent":{"__id__":4},"_components":[{"__type__":"cc.Sprite","node":{"__id__":6},"_spriteFrame":{"__uuid__":"f1q7CSgqVMfaarLCi2aDiI"}},{"__type__":"cc.Widget","node":{"__id__":6},"alignMode":0,"_alignFlags":12}],"_contentSize":{"__type__":"cc.Size","width":254,"height":187},"_anchorPoint":{"__type__":"cc.Vec2"},"_trs":{"__type__":"TypedArray","ctor":"Float64Array","array":[-360,-640,0,0,0,0,1,1.177,1.177,1]},"_zIndex":0},{"__type__":"cc.Node","_name":"match_background_rb","_parent":{"__id__":4},"_components":[{"__type__":"cc.Sprite","node":{"__id__":7},"_spriteFrame":{"__uuid__":"4eX2Qg5r1L6IR+lXq4R+R4"}},{"__type__":"cc.Widget","node":{"__id__":7},"alignMode":0,"_alignFlags":36}],"_contentSize":{"__type__":"cc.Size","width":250,"height":153},"_anchorPoint":{"__type__":"cc.Vec2","x":1},"_trs":{"__type__":"TypedArray","ctor":"Float64Array","array":[360,-640,0,0,0,0,1,1.177,1.177,1]},"_zIndex":0},{"__type__":"cc.Node","_name":"match_background_ml","_parent":{"__id__":4},"_components":[{"__type__":"cc.Sprite","node":{"__id__":8},"_spriteFrame":{"__uuid__":"c2fHHmTJhNRJd8NOssExAH"}}],"_contentSize":{"__type__":"cc.Size","width":41,"height":312},"_trs":{"__type__":"TypedArray","ctor":"Float64Array","array":[461.8,-327,0,0,0,0,1,1,1,1]},"_zIndex":0},{"__type__":"cc.Node","_name":"match_background_mr","_parent":{"__id__":4},"_components":[{"__type__":"cc.Sprite","node":{"__id__":9},"_spriteFrame":{"__uuid__":"fcNaV7w4FFUoY6acKaUvsG"}}],"_contentSize":{"__type__":"cc.Size","width":67,"height":273},"_trs":{"__type__":"TypedArray","ctor":"Float64Array","array":[-449,-194,0,0,0,0,1,1,1,1]},"_zIndex":0},{"__type__":"cc.Node","_name":"match_background_top_thumb","_parent":{"__id__":4},"_components":[{"__type__":"cc.Sprite","node":{"__id__":10},"_spriteFrame":{"__uuid__":"28WhKqAKhGM6cPUWDBq/1I"}}],"_contentSize":{"__type__":"cc.Size","width":77,"height":57},"_anchorPoint":{"__type__":"cc.Vec2","x":0.5,"y":0.52},"_trs":{"__type__":"TypedArray","ctor":"Float64Array","array":[0,367,0,0,0,0,1,10,10,1]},"_zIndex":0},{"__type__":"cc.Node","_name":"match_background_top","_parent":{"__id__":4},"_components":[{"__type__":"cc.Sprite","node":{"__id__":11},"_spriteFrame":{"__uuid__":"a1cdW060JObqw0glt0trnn"}}],"_contentSize":{"__type__":"cc.Size","width":768,"height":567},"_anchorPoint":{"__type__":"cc.Vec2","x":0.5,"y":0.52},"_trs":{"__type__":"TypedArray","ctor":"Float64Array","array":[0,367,0,0,0,0,1,1,1,1]},"_zIndex":0},{"__type__":"cc.Node","_name":"userInterfaceView","_parent":{"__id__":2},"_children":[{"__id__":13},{"__id__":85},{"__id__":86},{"__id__":87},{"__id__":88}],"_components":[{"__type__":"cc.Widget","node":{"__id__":12},"alignMode":0,"_alignFlags":45},{"__type__":"cc.Animation","node":{"__id__":12}}],"_contentSize":{"__type__":"cc.Size","width":720,"height":1280},"_trs":{"__type__":"TypedArray","ctor":"Float64Array","array":[0,0,0,0,0,0,1,1,1,1]},"_zIndex":0},{"__type__":"cc.Node","_name":"topRoot","_parent":{"__id__":12},"_children":[{"__id__":14},{"__id__":76}],"_components":[{"__type__":"cc.Widget","node":{"__id__":13},"alignMode":2,"_alignFlags":41,"_originalWidth":618}],"_contentSize":{"__type__":"cc.Size","width":720,"height":300},"_anchorPoint":{"__type__":"cc.Vec2","x":0.5,"y":1},"_trs":{"__type__":"TypedArray","ctor":"Float64Array","array":[0,640,0,0,0,0,1,1,1,1]},"_zIndex":0},{"__type__":"cc.Node","_name":"LeftFrame","_parent":{"__id__":13},"_children":[{"__id__":15},{"__id__":38}],"_components":[{"__type__":"cc.Widget","node":{"__id__":14},"alignMode":0,"_alignFlags":45}],"_contentSize":{"__type__":"cc.Size","width":720,"height":300},"_anchorPoint":{"__type__":"cc.Vec2","x":0.5,"y":1},"_trs":{"__type__":"TypedArray","ctor":"Float64Array","array":[0,0,0,0,0,0,1,1,1,1]},"_zIndex":0},{"__type__":"cc.Node","_name":"stepScoreBar","_parent":{"__id__":14},"_children":[{"__id__":16},{"__id__":17},{"__id__":21}],"_components":[{"__type__":"cc.Sprite","node":{"__id__":15},"_spriteFrame":{"__uuid__":"196Y2RFpVKyolkvPizsP2J"}},{"__type__":"cc.Widget","node":{"__id__":15},"alignMode":0,"_alignFlags":9}],"_contentSize":{"__type__":"cc.Size","width":125,"height":121},"_trs":{"__type__":"TypedArray","ctor":"Float64Array","array":[-297.5,-60.5,0,0,0,0,1,1,1,1]},"_zIndex":0},{"__type__":"cc.Node","_name":"UserInterface-iconStep","_parent":{"__id__":15},"_components":[{"__type__":"cc.Sprite","node":{"__id__":16},"_spriteFrame":{"__uuid__":"a8Ik+sk+ZE7YWZzwJqFKY1"},"_sizeMode":2,"_isTrimmedMode":false}],"_contentSize":{"__type__":"cc.Size","width":56,"height":17},"_trs":{"__type__":"TypedArray","ctor":"Float64Array","array":[-12,32,0,0,0,0,1,1,1,1]},"_zIndex":0},{"__type__":"cc.Node","_name":"StepBar","_parent":{"__id__":15},"_children":[{"__id__":18}],"_components":[{"__id__":20}],"_prefab":{"__type__":"cc.PrefabInfo","root":{"__id__":17},"asset":{"__uuid__":"1a5GIEiu1KcaRlyilR8EN0"},"fileId":"85lQOsV3lLrI2VsDy3IrzE"},"_trs":{"__type__":"TypedArray","ctor":"Float64Array","array":[-12,-5,0,0,0,0,1,1,1,1]},"_zIndex":0},{"__type__":"cc.Node","_name":"stepLabel","_parent":{"__id__":17},"_components":[{"__id__":19}],"_prefab":{"__type__":"cc.PrefabInfo","root":{"__id__":17},"asset":{"__uuid__":"1a5GIEiu1KcaRlyilR8EN0"},"fileId":"44YiRaHtdFlovjtgTcj6nK"},"_contentSize":{"__type__":"cc.Size","width":64.75,"height":43.75},"_trs":{"__type__":"TypedArray","ctor":"Float64Array","array":[0,0,0,0,0,0,1,1,1,1]},"_zIndex":0},{"__type__":"cc.Label","node":{"__id__":18},"_useOriginalSize":false,"_string":"23","_N$string":"23","_fontSize":28,"_lineHeight":50,"_N$file":{"__uuid__":"59NhtwzxRMHpAKAv6l4S/U"},"_isSystemFontUsed":false},{"__type__":"4f2b4DLb1RESaYZOVpmg6N8","node":{"__id__":17},"label":{"__id__":19}},{"__type__":"cc.Node","_name":"ScoreBar","_parent":{"__id__":15},"_children":[{"__id__":22}],"_components":[{"__id__":37}],"_prefab":{"__type__":"cc.PrefabInfo","root":{"__id__":21},"asset":{"__uuid__":"0f+K9hqPFFArIvXGVtwCs/"},"fileId":"85lQOsV3lLrI2VsDy3IrzE"},"_trs":{"__type__":"TypedArray","ctor":"Float64Array","array":[-42.1,44.6,0,0,0,0,1,1,1,1]},"_zIndex":0},{"__type__":"cc.Node","_name":"progressBar","_parent":{"__id__":21},"_children":[{"__id__":23},{"__id__":24},{"__id__":26},{"__id__":28},{"__id__":30},{"__id__":32},{"__id__":34}],"_components":[{"__type__":"cc.Sprite","node":{"__id__":22},"_type":1,"_sizeMode":2,"_isTrimmedMode":false},{"__id__":36}],"_prefab":{"__type__":"cc.PrefabInfo","root":{"__id__":21},"asset":{"__uuid__":"0f+K9hqPFFArIvXGVtwCs/"},"fileId":"23xCFumPlEkI4rdxnfbPcR"},"_contentSize":{"__type__":"cc.Size","width":102,"height":102},"_trs":{"__type__":"TypedArray","ctor":"Float64Array","array":[0,0,0,0,0,0,1,1,1,1]},"_zIndex":0},{"__type__":"cc.Node","_name":"match_star_progress_back","_parent":{"__id__":22},"_components":[{"__type__":"cc.Sprite","node":{"__id__":23},"_spriteFrame":{"__uuid__":"e29NXfhkdDva/XjSanFjvC"}}],"_prefab":{"__type__":"cc.PrefabInfo","root":{"__id__":21},"asset":{"__uuid__":"0f+K9hqPFFArIvXGVtwCs/"},"fileId":"c2kzIHg9xOBL1MrOvAhmDW"},"_contentSize":{"__type__":"cc.Size","width":149,"height":145},"_trs":{"__type__":"TypedArray","ctor":"Float64Array","array":[53,-55,0,0,0,0,1,1,1,1]},"_zIndex":0},{"__type__":"cc.Node","_name":"bar","_parent":{"__id__":22},"_components":[{"__id__":25}],"_prefab":{"__type__":"cc.PrefabInfo","root":{"__id__":21},"asset":{"__uuid__":"0f+K9hqPFFArIvXGVtwCs/"},"fileId":"58rr/YgNZNYLzQRsXyQdVI"},"_contentSize":{"__type__":"cc.Size","width":228,"height":228},"_trs":{"__type__":"TypedArray","ctor":"Float64Array","array":[0,0,0,0,0,0,1,1,1,1]},"_zIndex":0},{"__type__":"cc.Sprite","node":{"__id__":24},"_spriteFrame":{"__uuid__":"35IqDHPfZL15xxSGqvXc6w"},"_type":3,"_sizeMode":2,"_fillType":2,"_fillCenter":{"__type__":"cc.Vec2","x":0.5,"y":0.5},"_fillStart":0.714,"_fillRange":0.315,"_isTrimmedMode":false},{"__type__":"cc.Node","_name":"pointer","_parent":{"__id__":22},"_children":[{"__id__":27}],"_prefab":{"__type__":"cc.PrefabInfo","root":{"__id__":21},"asset":{"__uuid__":"0f+K9hqPFFArIvXGVtwCs/"},"fileId":"77pIVWDOxJ+4iARrM+Pop+"},"_trs":{"__type__":"TypedArray","ctor":"Float64Array","array":[0,0,0,0,0,0,1,1,1,1]},"_eulerAngles":{"__type__":"cc.Vec3","z":10},"_zIndex":0},{"__type__":"cc.Node","_name":"match_star_progress_top","_parent":{"__id__":26},"_components":[{"__type__":"cc.Sprite","node":{"__id__":27},"_spriteFrame":{"__uuid__":"17+NA02MpMqIMArk6F0Fza"}}],"_prefab":{"__type__":"cc.PrefabInfo","root":{"__id__":21},"asset":{"__uuid__":"0f+K9hqPFFArIvXGVtwCs/"},"fileId":"28vODE+mNFbYsHN+e5waab"},"_contentSize":{"__type__":"cc.Size","width":11,"height":28},"_trs":{"__type__":"TypedArray","ctor":"Float64Array","array":[103.5,0,0,0,0,0,1,1,1,1]},"_eulerAngles":{"__type__":"cc.Vec3","z":90},"_zIndex":0},{"__type__":"cc.Node","_name":"star0","_parent":{"__id__":22},"_components":[{"__id__":29}],"_prefab":{"__type__":"cc.PrefabInfo","root":{"__id__":21},"asset":{"__uuid__":"0f+K9hqPFFArIvXGVtwCs/"},"fileId":"b1CJghDopGeKt65zhIFH5D"},"_contentSize":{"__type__":"cc.Size","width":40,"height":39},"_trs":{"__type__":"TypedArray","ctor":"Float64Array","array":[70,-92,0,0,0,0,1,1,1,1]},"_zIndex":0},{"__type__":"cc.Sprite","node":{"__id__":28},"_spriteFrame":{"__uuid__":"55yJEeYXFNTYDl/8x0noLp"}},{"__type__":"cc.Node","_name":"star1","_parent":{"__id__":22},"_components":[{"__id__":31}],"_prefab":{"__type__":"cc.PrefabInfo","root":{"__id__":21},"asset":{"__uuid__":"0f+K9hqPFFArIvXGVtwCs/"},"fileId":"7aO2PWdlNDF6IZMJ60vunx"},"_contentSize":{"__type__":"cc.Size","width":40,"height":39},"_trs":{"__type__":"TypedArray","ctor":"Float64Array","array":[102,-56,0,0,0,0,1,1,1,1]},"_zIndex":0},{"__type__":"cc.Sprite","node":{"__id__":30},"_spriteFrame":{"__uuid__":"55yJEeYXFNTYDl/8x0noLp"}},{"__type__":"cc.Node","_name":"star2","_parent":{"__id__":22},"_components":[{"__id__":33}],"_prefab":{"__type__":"cc.PrefabInfo","root":{"__id__":21},"asset":{"__uuid__":"0f+K9hqPFFArIvXGVtwCs/"},"fileId":"8e0fBueQpOnrlTqMQ8FF+f"},"_contentSize":{"__type__":"cc.Size","width":40,"height":39},"_trs":{"__type__":"TypedArray","ctor":"Float64Array","array":[118,-10,0,0,0,0,1,1,1,1]},"_zIndex":0},{"__type__":"cc.Sprite","node":{"__id__":32},"_spriteFrame":{"__uuid__":"55yJEeYXFNTYDl/8x0noLp"}},{"__type__":"cc.Node","_name":"scoreLabel","_parent":{"__id__":22},"_components":[{"__id__":35}],"_prefab":{"__type__":"cc.PrefabInfo","root":{"__id__":21},"asset":{"__uuid__":"0f+K9hqPFFArIvXGVtwCs/"},"fileId":"7b/muJvHBEV6UN7fwXcJAO"},"_contentSize":{"__type__":"cc.Size","width":100,"height":30},"_anchorPoint":{"__type__":"cc.Vec2","y":0.5},"_trs":{"__type__":"TypedArray","ctor":"Float64Array","array":[-20,-132,0,0,0,0,1,0.8,0.8,1]},"_zIndex":0},{"__type__":"cc.Label","node":{"__id__":34},"_useOriginalSize":false,"_string":"999999","_N$string":"999999","_fontSize":28,"_lineHeight":20.8,"_N$file":{"__uuid__":"96/Cmi4OpC2IkOdTDlMLwZ"},"_isSystemFontUsed":false,"_N$horizontalAlign":1,"_N$verticalAlign":1,"_N$overflow":1},{"__type__":"cc.ProgressBar","node":{"__id__":22},"_N$totalLength":0.315,"_N$barSprite":{"__id__":25},"_N$mode":2},{"__type__":"2556aN17LhENoC3iiVSOFb4","node":{"__id__":21},"progressBar":{"__id__":36},"pointer":{"__id__":26},"pointerHead":{"__id__":27},"scoreLabel":{"__id__":35},"stars":[{"__id__":29},{"__id__":31},{"__id__":33}]},{"__type__":"cc.Node","_name":"CollectedTrainSupplyBar","_parent":{"__id__":14},"_children":[{"__id__":39},{"__id__":46},{"__id__":61},{"__id__":68}],"_components":[{"__type__":"cc.Layout","node":{"__id__":38},"_layoutSize":{"__type__":"cc.Size","width":312,"height":80},"_resize":1,"_N$layoutType":1,"_N$spacingX":3},{"__id__":75},{"__type__":"cc.Widget","node":{"__id__":38},"alignMode":0,"_alignFlags":12,"_left":6,"_bottom":5}],"_prefab":{"__type__":"cc.PrefabInfo","root":{"__id__":38},"asset":{"__uuid__":"77jApIOjRDqLRod857XIb8"},"fileId":"85lQOsV3lLrI2VsDy3IrzE"},"_contentSize":{"__type__":"cc.Size","width":312,"height":80},"_trs":{"__type__":"TypedArray","ctor":"Float64Array","array":[-213.6,-259,0,0,0,0,1,0.9,0.9,1]},"_zIndex":0},{"__type__":"cc.Node","_name":"Food","_parent":{"__id__":38},"_children":[{"__id__":40}],"_components":[{"__type__":"45dbbBZpypLmKH4Ia8SlBQb","node":{"__id__":39},"icon":{"__id__":43},"amountLabel":{"__id__":45}},{"__type__":"27f1ez202tMP7oxJ80RscXS","node":{"__id__":39},"identifier":"MatchScene_FoodIcon"}],"_prefab":{"__type__":"cc.PrefabInfo","root":{"__id__":38},"asset":{"__uuid__":"77jApIOjRDqLRod857XIb8"},"fileId":"5asZopxD5AmJexgrOHhtTM"},"_contentSize":{"__type__":"cc.Size","width":60,"height":70},"_trs":{"__type__":"TypedArray","ctor":"Float64Array","array":[-126,0,0,0,0,0,1,1,1,1]},"_zIndex":0},{"__type__":"cc.Node","_name":"match_ico_dk","_parent":{"__id__":39},"_children":[{"__id__":41},{"__id__":44}],"_components":[{"__type__":"cc.Sprite","node":{"__id__":40},"_spriteFrame":{"__uuid__":"f8ynjAm6xEwKZgn54+WvjB"}}],"_prefab":{"__type__":"cc.PrefabInfo","root":{"__id__":38},"asset":{"__uuid__":"77jApIOjRDqLRod857XIb8"},"fileId":"93OQFB0Y5NSI23MChnxlmI"},"_contentSize":{"__type__":"cc.Size","width":98,"height":98},"_trs":{"__type__":"TypedArray","ctor":"Float64Array","array":[0,0,0,0,0,0,1,0.6,0.6,1]},"_zIndex":0},{"__type__":"cc.Node","_name":"iconRoot","_parent":{"__id__":40},"_children":[{"__id__":42}],"_prefab":{"__type__":"cc.PrefabInfo","root":{"__id__":38},"asset":{"__uuid__":"77jApIOjRDqLRod857XIb8"},"fileId":"20NwvMhKtLxoKiNlYSmFrW"},"_trs":{"__type__":"TypedArray","ctor":"Float64Array","array":[0,0,0,0,0,0,1,0.7,0.7,1]},"_zIndex":0},{"__type__":"cc.Node","_name":"icon","_parent":{"__id__":41},"_components":[{"__id__":43},{"__type__":"f41c7fUzppLL5BL0ZHlFDVT","node":{"__id__":42}}],"_prefab":{"__type__":"cc.PrefabInfo","root":{"__id__":38},"asset":{"__uuid__":"77jApIOjRDqLRod857XIb8"},"fileId":"ceDC+HMgJFcJ/JsDH8lG1k"},"_contentSize":{"__type__":"cc.Size","width":117,"height":117},"_trs":{"__type__":"TypedArray","ctor":"Float64Array","array":[0,0,0,0,0,0,1,1,1,1]},"_zIndex":0},{"__type__":"cc.Sprite","node":{"__id__":42},"_spriteFrame":{"__uuid__":"97IiCgPJtATb0TbEvBFJvG"},"_sizeMode":2,"_isTrimmedMode":false},{"__type__":"cc.Node","_name":"amountLabel","_parent":{"__id__":40},"_components":[{"__id__":45}],"_prefab":{"__type__":"cc.PrefabInfo","root":{"__id__":38},"asset":{"__uuid__":"77jApIOjRDqLRod857XIb8"},"fileId":"f9J1XDqbpJU6U7H6p89Xfk"},"_contentSize":{"__type__":"cc.Size","width":50,"height":18},"_anchorPoint":{"__type__":"cc.Vec2","x":1,"y":0.5},"_trs":{"__type__":"TypedArray","ctor":"Float64Array","array":[40,-24,0,0,0,0,1,1,1,1]},"_zIndex":0},{"__type__":"cc.Label","node":{"__id__":44},"_useOriginalSize":false,"_string":"108","_N$string":"108","_fontSize":32,"_lineHeight":18,"_N$file":{"__uuid__":"96/Cmi4OpC2IkOdTDlMLwZ"},"_isSystemFontUsed":false,"_N$horizontalAlign":1,"_N$verticalAlign":1},{"__type__":"cc.Node","_name":"SoapAndEyepatch","_parent":{"__id__":38},"_children":[{"__id__":47},{"__id__":54}],"_components":[{"__type__":"27f1ez202tMP7oxJ80RscXS","node":{"__id__":46},"identifier":"MatchScene_SoapAndEyepatchIcon"}],"_prefab":{"__type__":"cc.PrefabInfo","root":{"__id__":38},"asset":{"__uuid__":"77jApIOjRDqLRod857XIb8"},"fileId":"82+8fuXOBExLlHyyHnV5iG"},"_contentSize":{"__type__":"cc.Size","width":123,"height":70},"_trs":{"__type__":"TypedArray","ctor":"Float64Array","array":[-31.5,0,0,0,0,0,1,1,1,1]},"_zIndex":0},{"__type__":"cc.Node","_name":"Soap","_parent":{"__id__":46},"_children":[{"__id__":48}],"_components":[{"__type__":"45dbbBZpypLmKH4Ia8SlBQb","node":{"__id__":47},"icon":{"__id__":51},"amountLabel":{"__id__":53}},{"__type__":"27f1ez202tMP7oxJ80RscXS","node":{"__id__":47},"identifier":"MatchScene_SoapIcon"}],"_prefab":{"__type__":"cc.PrefabInfo","root":{"__id__":38},"asset":{"__uuid__":"77jApIOjRDqLRod857XIb8"},"fileId":"acz9ProeFDKrGNGa1a3WLo"},"_contentSize":{"__type__":"cc.Size","width":60,"height":70},"_trs":{"__type__":"TypedArray","ctor":"Float64Array","array":[-31.5,0,0,0,0,0,1,1,1,1]},"_zIndex":0},{"__type__":"cc.Node","_name":"match_ico_dk","_parent":{"__id__":47},"_children":[{"__id__":49},{"__id__":52}],"_components":[{"__type__":"cc.Sprite","node":{"__id__":48},"_spriteFrame":{"__uuid__":"f8ynjAm6xEwKZgn54+WvjB"}}],"_prefab":{"__type__":"cc.PrefabInfo","root":{"__id__":38},"asset":{"__uuid__":"77jApIOjRDqLRod857XIb8"},"fileId":"090nx0w71E2avBnTxw4lJx"},"_contentSize":{"__type__":"cc.Size","width":98,"height":98},"_trs":{"__type__":"TypedArray","ctor":"Float64Array","array":[0,0,0,0,0,0,1,0.6,0.6,1]},"_zIndex":0},{"__type__":"cc.Node","_name":"iconRoot","_parent":{"__id__":48},"_children":[{"__id__":50}],"_prefab":{"__type__":"cc.PrefabInfo","root":{"__id__":38},"asset":{"__uuid__":"77jApIOjRDqLRod857XIb8"},"fileId":"87Mk7LQ/VKGJhlTxT414AG"},"_trs":{"__type__":"TypedArray","ctor":"Float64Array","array":[0,0,0,0,0,0,1,0.7,0.7,1]},"_zIndex":0},{"__type__":"cc.Node","_name":"icon","_parent":{"__id__":49},"_components":[{"__id__":51},{"__type__":"f41c7fUzppLL5BL0ZHlFDVT","node":{"__id__":50}}],"_prefab":{"__type__":"cc.PrefabInfo","root":{"__id__":38},"asset":{"__uuid__":"77jApIOjRDqLRod857XIb8"},"fileId":"11hQGIOmVPzL1BPHT2D6ue"},"_contentSize":{"__type__":"cc.Size","width":117,"height":117},"_trs":{"__type__":"TypedArray","ctor":"Float64Array","array":[0,0,0,0,0,0,1,1,1,1]},"_zIndex":0},{"__type__":"cc.Sprite","node":{"__id__":50},"_spriteFrame":{"__uuid__":"97IiCgPJtATb0TbEvBFJvG"},"_sizeMode":2,"_isTrimmedMode":false},{"__type__":"cc.Node","_name":"amountLabel","_parent":{"__id__":48},"_components":[{"__id__":53}],"_prefab":{"__type__":"cc.PrefabInfo","root":{"__id__":38},"asset":{"__uuid__":"77jApIOjRDqLRod857XIb8"},"fileId":"dfvm5yvkNNdo+6qMyXm2cO"},"_contentSize":{"__type__":"cc.Size","width":50,"height":18},"_anchorPoint":{"__type__":"cc.Vec2","x":1,"y":0.5},"_trs":{"__type__":"TypedArray","ctor":"Float64Array","array":[40,-24,0,0,0,0,1,1,1,1]},"_zIndex":0},{"__type__":"cc.Label","node":{"__id__":52},"_useOriginalSize":false,"_string":"108","_N$string":"108","_fontSize":32,"_lineHeight":18,"_N$file":{"__uuid__":"96/Cmi4OpC2IkOdTDlMLwZ"},"_isSystemFontUsed":false,"_N$horizontalAlign":1,"_N$verticalAlign":1},{"__type__":"cc.Node","_name":"Eyepatch","_parent":{"__id__":46},"_children":[{"__id__":55}],"_components":[{"__type__":"45dbbBZpypLmKH4Ia8SlBQb","node":{"__id__":54},"icon":{"__id__":58},"amountLabel":{"__id__":60}},{"__type__":"27f1ez202tMP7oxJ80RscXS","node":{"__id__":54},"identifier":"MatchScene_EyepatchIcon"}],"_prefab":{"__type__":"cc.PrefabInfo","root":{"__id__":38},"asset":{"__uuid__":"77jApIOjRDqLRod857XIb8"},"fileId":"0fpVjOimpE462630SuFVEv"},"_contentSize":{"__type__":"cc.Size","width":60,"height":70},"_trs":{"__type__":"TypedArray","ctor":"Float64Array","array":[31.5,0,0,0,0,0,1,1.1111111,1.1111111,1]},"_zIndex":0},{"__type__":"cc.Node","_name":"match_ico_dk","_parent":{"__id__":54},"_children":[{"__id__":56},{"__id__":59}],"_components":[{"__type__":"cc.Sprite","node":{"__id__":55},"_spriteFrame":{"__uuid__":"f8ynjAm6xEwKZgn54+WvjB"}}],"_prefab":{"__type__":"cc.PrefabInfo","root":{"__id__":38},"asset":{"__uuid__":"77jApIOjRDqLRod857XIb8"},"fileId":"34kPvJDaVH9Z1ceYmVEj6u"},"_contentSize":{"__type__":"cc.Size","width":98,"height":98},"_trs":{"__type__":"TypedArray","ctor":"Float64Array","array":[0,0,0,0,0,0,1,0.6,0.6,1]},"_zIndex":0},{"__type__":"cc.Node","_name":"iconRoot","_parent":{"__id__":55},"_children":[{"__id__":57}],"_prefab":{"__type__":"cc.PrefabInfo","root":{"__id__":38},"asset":{"__uuid__":"77jApIOjRDqLRod857XIb8"},"fileId":"f8QKcaxhRFAZKTf41pZGC3"},"_trs":{"__type__":"TypedArray","ctor":"Float64Array","array":[0,0,0,0,0,0,1,0.7,0.7,1]},"_zIndex":0},{"__type__":"cc.Node","_name":"icon","_parent":{"__id__":56},"_components":[{"__id__":58},{"__type__":"f41c7fUzppLL5BL0ZHlFDVT","node":{"__id__":57}}],"_prefab":{"__type__":"cc.PrefabInfo","root":{"__id__":38},"asset":{"__uuid__":"77jApIOjRDqLRod857XIb8"},"fileId":"78/RwtWjZAhKrAT1qU64yX"},"_contentSize":{"__type__":"cc.Size","width":117,"height":117},"_trs":{"__type__":"TypedArray","ctor":"Float64Array","array":[0,0,0,0,0,0,1,1,1,1]},"_zIndex":0},{"__type__":"cc.Sprite","node":{"__id__":57},"_spriteFrame":{"__uuid__":"97IiCgPJtATb0TbEvBFJvG"},"_sizeMode":2,"_isTrimmedMode":false},{"__type__":"cc.Node","_name":"amountLabel","_parent":{"__id__":55},"_components":[{"__id__":60}],"_prefab":{"__type__":"cc.PrefabInfo","root":{"__id__":38},"asset":{"__uuid__":"77jApIOjRDqLRod857XIb8"},"fileId":"57XeLXvd9FqIrCvo2xVZaA"},"_contentSize":{"__type__":"cc.Size","width":50,"height":18},"_anchorPoint":{"__type__":"cc.Vec2","x":1,"y":0.5},"_trs":{"__type__":"TypedArray","ctor":"Float64Array","array":[40,-24,0,0,0,0,1,1,1,1]},"_zIndex":0},{"__type__":"cc.Label","node":{"__id__":59},"_useOriginalSize":false,"_string":"108","_N$string":"108","_fontSize":32,"_lineHeight":18,"_N$file":{"__uuid__":"96/Cmi4OpC2IkOdTDlMLwZ"},"_isSystemFontUsed":false,"_N$horizontalAlign":1,"_N$verticalAlign":1},{"__type__":"cc.Node","_name":"Hoe","_parent":{"__id__":38},"_children":[{"__id__":62}],"_components":[{"__type__":"45dbbBZpypLmKH4Ia8SlBQb","node":{"__id__":61},"icon":{"__id__":65},"amountLabel":{"__id__":67}},{"__type__":"27f1ez202tMP7oxJ80RscXS","node":{"__id__":61},"identifier":"MatchScene_HoeIcon"}],"_prefab":{"__type__":"cc.PrefabInfo","root":{"__id__":38},"asset":{"__uuid__":"77jApIOjRDqLRod857XIb8"},"fileId":"9cUYJv3m1C85eREcWf0iuJ"},"_contentSize":{"__type__":"cc.Size","width":60,"height":70},"_trs":{"__type__":"TypedArray","ctor":"Float64Array","array":[63,0,0,0,0,0,1,1,1,1]},"_zIndex":0},{"__type__":"cc.Node","_name":"match_ico_dk","_parent":{"__id__":61},"_children":[{"__id__":63},{"__id__":66}],"_components":[{"__type__":"cc.Sprite","node":{"__id__":62},"_spriteFrame":{"__uuid__":"f8ynjAm6xEwKZgn54+WvjB"}}],"_prefab":{"__type__":"cc.PrefabInfo","root":{"__id__":38},"asset":{"__uuid__":"77jApIOjRDqLRod857XIb8"},"fileId":"cfeF4yky1AqL1YwwTquyCf"},"_contentSize":{"__type__":"cc.Size","width":98,"height":98},"_trs":{"__type__":"TypedArray","ctor":"Float64Array","array":[0,0,0,0,0,0,1,0.6,0.6,1]},"_zIndex":0},{"__type__":"cc.Node","_name":"iconRoot","_parent":{"__id__":62},"_children":[{"__id__":64}],"_prefab":{"__type__":"cc.PrefabInfo","root":{"__id__":38},"asset":{"__uuid__":"77jApIOjRDqLRod857XIb8"},"fileId":"30syIJfc9MjrqEw4U3/FQI"},"_trs":{"__type__":"TypedArray","ctor":"Float64Array","array":[0,0,0,0,0,0,1,0.7,0.7,1]},"_zIndex":0},{"__type__":"cc.Node","_name":"icon","_parent":{"__id__":63},"_components":[{"__id__":65},{"__type__":"f41c7fUzppLL5BL0ZHlFDVT","node":{"__id__":64}}],"_prefab":{"__type__":"cc.PrefabInfo","root":{"__id__":38},"asset":{"__uuid__":"77jApIOjRDqLRod857XIb8"},"fileId":"fd/pAe/CpDvYMqT/n/oO+p"},"_contentSize":{"__type__":"cc.Size","width":117,"height":117},"_trs":{"__type__":"TypedArray","ctor":"Float64Array","array":[0,0,0,0,0,0,1,1,1,1]},"_zIndex":0},{"__type__":"cc.Sprite","node":{"__id__":64},"_spriteFrame":{"__uuid__":"97IiCgPJtATb0TbEvBFJvG"},"_sizeMode":2,"_isTrimmedMode":false},{"__type__":"cc.Node","_name":"amountLabel","_parent":{"__id__":62},"_components":[{"__id__":67}],"_prefab":{"__type__":"cc.PrefabInfo","root":{"__id__":38},"asset":{"__uuid__":"77jApIOjRDqLRod857XIb8"},"fileId":"49FtNkgNRNW5B310llZrWD"},"_contentSize":{"__type__":"cc.Size","width":50,"height":18},"_anchorPoint":{"__type__":"cc.Vec2","x":1,"y":0.5},"_trs":{"__type__":"TypedArray","ctor":"Float64Array","array":[40,-24,0,0,0,0,1,1,1,1]},"_zIndex":0},{"__type__":"cc.Label","node":{"__id__":66},"_useOriginalSize":false,"_string":"108","_N$string":"108","_fontSize":32,"_lineHeight":18,"_N$file":{"__uuid__":"96/Cmi4OpC2IkOdTDlMLwZ"},"_isSystemFontUsed":false,"_N$horizontalAlign":1,"_N$verticalAlign":1},{"__type__":"cc.Node","_name":"Coin","_parent":{"__id__":38},"_children":[{"__id__":69}],"_components":[{"__type__":"45dbbBZpypLmKH4Ia8SlBQb","node":{"__id__":68},"icon":{"__id__":72},"amountLabel":{"__id__":74}},{"__type__":"27f1ez202tMP7oxJ80RscXS","node":{"__id__":68},"identifier":"MatchScene_CoinIcon"}],"_prefab":{"__type__":"cc.PrefabInfo","root":{"__id__":38},"asset":{"__uuid__":"77jApIOjRDqLRod857XIb8"},"fileId":"beRpKyMKxAZrJs+SKJr1ET"},"_contentSize":{"__type__":"cc.Size","width":60,"height":70},"_trs":{"__type__":"TypedArray","ctor":"Float64Array","array":[126,0,0,0,0,0,1,1,1,1]},"_zIndex":0},{"__type__":"cc.Node","_name":"match_ico_dk","_parent":{"__id__":68},"_children":[{"__id__":70},{"__id__":73}],"_components":[{"__type__":"cc.Sprite","node":{"__id__":69},"_spriteFrame":{"__uuid__":"f8ynjAm6xEwKZgn54+WvjB"}}],"_prefab":{"__type__":"cc.PrefabInfo","root":{"__id__":38},"asset":{"__uuid__":"77jApIOjRDqLRod857XIb8"},"fileId":"f0pFCaqH9DHIhYOmtV92tj"},"_contentSize":{"__type__":"cc.Size","width":98,"height":98},"_trs":{"__type__":"TypedArray","ctor":"Float64Array","array":[0,0,0,0,0,0,1,0.6,0.6,1]},"_zIndex":0},{"__type__":"cc.Node","_name":"iconRoot","_parent":{"__id__":69},"_children":[{"__id__":71}],"_prefab":{"__type__":"cc.PrefabInfo","root":{"__id__":38},"asset":{"__uuid__":"77jApIOjRDqLRod857XIb8"},"fileId":"49L/ddxl9NQ4yq27SVEx19"},"_trs":{"__type__":"TypedArray","ctor":"Float64Array","array":[0,0,0,0,0,0,1,0.7,0.7,1]},"_zIndex":0},{"__type__":"cc.Node","_name":"icon","_parent":{"__id__":70},"_components":[{"__id__":72},{"__type__":"f41c7fUzppLL5BL0ZHlFDVT","node":{"__id__":71}}],"_prefab":{"__type__":"cc.PrefabInfo","root":{"__id__":38},"asset":{"__uuid__":"77jApIOjRDqLRod857XIb8"},"fileId":"2eZGp97PlIPblrgDpAHT1h"},"_contentSize":{"__type__":"cc.Size","width":117,"height":117},"_trs":{"__type__":"TypedArray","ctor":"Float64Array","array":[0,0,0,0,0,0,1,1,1,1]},"_zIndex":0},{"__type__":"cc.Sprite","node":{"__id__":71},"_spriteFrame":{"__uuid__":"97IiCgPJtATb0TbEvBFJvG"},"_sizeMode":2,"_isTrimmedMode":false},{"__type__":"cc.Node","_name":"amountLabel","_parent":{"__id__":69},"_components":[{"__id__":74}],"_prefab":{"__type__":"cc.PrefabInfo","root":{"__id__":38},"asset":{"__uuid__":"77jApIOjRDqLRod857XIb8"},"fileId":"90IVfbgzFMaK921UWNQ/dd"},"_contentSize":{"__type__":"cc.Size","width":50,"height":18},"_anchorPoint":{"__type__":"cc.Vec2","x":1,"y":0.5},"_trs":{"__type__":"TypedArray","ctor":"Float64Array","array":[40,-24,0,0,0,0,1,1,1,1]},"_zIndex":0},{"__type__":"cc.Label","node":{"__id__":73},"_useOriginalSize":false,"_string":"108","_N$string":"108","_fontSize":32,"_lineHeight":18,"_N$file":{"__uuid__":"96/Cmi4OpC2IkOdTDlMLwZ"},"_isSystemFontUsed":false,"_N$horizontalAlign":1,"_N$verticalAlign":1},{"__type__":"c9815tJQWNIv4JFHwUMBuvr","node":{"__id__":38},"itemNodes":[{"__id__":39},{"__id__":47},{"__id__":54},{"__id__":61},{"__id__":68}]},{"__type__":"cc.Node","_name":"RightFrame","_parent":{"__id__":13},"_children":[{"__id__":77}],"_components":[{"__type__":"cc.Widget","node":{"__id__":76},"alignMode":0,"_alignFlags":45}],"_contentSize":{"__type__":"cc.Size","width":720,"height":300},"_anchorPoint":{"__type__":"cc.Vec2","x":0.5,"y":1},"_trs":{"__type__":"TypedArray","ctor":"Float64Array","array":[0,0,0,0,0,0,1,1,1,1]},"_zIndex":0},{"__type__":"cc.Node","_name":"targetBar","_parent":{"__id__":76},"_children":[{"__id__":78},{"__id__":83}],"_components":[{"__type__":"cc.Sprite","node":{"__id__":77},"_spriteFrame":{"__uuid__":"4bY3AZLzNOWZcwRPAiGT82"}},{"__type__":"cc.Widget","node":{"__id__":77},"alignMode":0,"_alignFlags":33,"_top":140}],"_contentSize":{"__type__":"cc.Size","width":234,"height":161},"_trs":{"__type__":"TypedArray","ctor":"Float64Array","array":[243,-220.5,0,0,0,0,1,1,1,1]},"_zIndex":0},{"__type__":"cc.Node","_name":"levelFrame","_parent":{"__id__":77},"_children":[{"__id__":79},{"__id__":80},{"__id__":82}],"_components":[{"__type__":"cc.Layout","node":{"__id__":78},"_layoutSize":{"__type__":"cc.Size","width":90.81,"height":30},"_resize":1,"_N$layoutType":1}],"_contentSize":{"__type__":"cc.Size","width":90.81,"height":30},"_trs":{"__type__":"TypedArray","ctor":"Float64Array","array":[0.2,46.9,0,0,0,0,1,1,1,1]},"_eulerAngles":{"__type__":"cc.Vec3","z":-4},"_zIndex":0},{"__type__":"cc.Node","_name":"match_level_di","_parent":{"__id__":78},"_components":[{"__type__":"cc.Sprite","node":{"__id__":79},"_spriteFrame":{"__uuid__":"50ZCz3WEtEQbDg0YBliw3A"}}],"_contentSize":{"__type__":"cc.Size","width":21,"height":23},"_trs":{"__type__":"TypedArray","ctor":"Float64Array","array":[-34.905,0,0,0,0,0,1,1,1,1]},"_zIndex":0},{"__type__":"cc.Node","_name":"levelLabel","_parent":{"__id__":78},"_components":[{"__id__":81}],"_contentSize":{"__type__":"cc.Size","width":47.81,"height":20.63},"_trs":{"__type__":"TypedArray","ctor":"Float64Array","array":[-0.5,0,0,0,0,0,1,1,1,1]},"_zIndex":0},{"__type__":"cc.Label","node":{"__id__":80},"_useOriginalSize":false,"_string":"222","_N$string":"222","_fontSize":30,"_lineHeight":22,"_N$file":{"__uuid__":"96/Cmi4OpC2IkOdTDlMLwZ"},"_isSystemFontUsed":false},{"__type__":"cc.Node","_name":"mathc_level_guan","_parent":{"__id__":78},"_components":[{"__type__":"cc.Sprite","node":{"__id__":82},"_spriteFrame":{"__uuid__":"2bHvaszytKn49UvJr00vPk"}}],"_contentSize":{"__type__":"cc.Size","width":22,"height":23},"_trs":{"__type__":"TypedArray","ctor":"Float64Array","array":[34.405,0,0,0,0,0,1,1,1,1]},"_zIndex":0},{"__type__":"cc.Node","_name":"TargetBar","_parent":{"__id__":77},"_components":[{"__type__":"cc.Layout","node":{"__id__":83},"_layoutSize":{"__type__":"cc.Size","width":246,"height":90},"_resize":1,"_N$layoutType":1,"_N$spacingX":2},{"__id__":84},{"__type__":"27f1ez202tMP7oxJ80RscXS","node":{"__id__":83},"identifier":"MatchScene_TargetBar"}],"_contentSize":{"__type__":"cc.Size","width":246,"height":90},"_trs":{"__type__":"TypedArray","ctor":"Float64Array","array":[-1.8,0.5,0,0,0,0,1,0.8,0.8,1]},"_eulerAngles":{"__type__":"cc.Vec3","z":-3},"_zIndex":0},{"__type__":"65ffdBK1NNNbolpzsnARDwo","node":{"__id__":83}},{"__type__":"cc.Node","_name":"cancelGearLayer","_parent":{"__id__":12},"_components":[{"__type__":"cc.Widget","node":{"__id__":85},"alignMode":2,"_target":{"__id__":2},"_alignFlags":45,"_originalWidth":100,"_originalHeight":100},{"__type__":"cc.BlockInputEvents","node":{"__id__":85}},{"__type__":"cc.Sprite","node":{"__id__":85},"_spriteFrame":{"__uuid__":"60nTL9hAxEm4C2zCTubRWC"},"_type":1,"_sizeMode":0}],"_opacity":0,"_color":{"__type__":"cc.Color"},"_contentSize":{"__type__":"cc.Size","width":720,"height":1280},"_trs":{"__type__":"TypedArray","ctor":"Float64Array","array":[0,0,0,0,0,0,1,1,1,1]},"_zIndex":0},{"__type__":"cc.Node","_name":"backgroundMask","_parent":{"__id__":12},"_components":[{"__type__":"cc.Widget","node":{"__id__":86},"alignMode":2,"_target":{"__id__":2},"_alignFlags":45,"_originalWidth":100,"_originalHeight":100},{"__type__":"cc.Sprite","node":{"__id__":86},"_spriteFrame":{"__uuid__":"60nTL9hAxEm4C2zCTubRWC"},"_sizeMode":0}],"_opacity":0,"_color":{"__type__":"cc.Color"},"_contentSize":{"__type__":"cc.Size","width":720,"height":1280},"_trs":{"__type__":"TypedArray","ctor":"Float64Array","array":[0,0,0,0,0,0,1,1,1,1]},"_zIndex":0},{"__type__":"cc.Node","_name":"matchGridView","_parent":{"__id__":12},"_components":[{"__type__":"cc.Widget","node":{"__id__":87},"alignMode":0,"_alignFlags":45,"_top":300,"_bottom":200,"_originalWidth":300,"_originalHeight":300}],"_contentSize":{"__type__":"cc.Size","width":720,"height":780},"_trs":{"__type__":"TypedArray","ctor":"Float64Array","array":[0,-50,0,0,0,0,1,1,1,1]},"_zIndex":0},{"__type__":"cc.Node","_name":"bottomRoot","_parent":{"__id__":12},"_children":[{"__id__":89}],"_components":[{"__type__":"cc.Widget","node":{"__id__":88},"alignMode":2,"_alignFlags":45,"_originalWidth":706,"_originalHeight":159}],"_contentSize":{"__type__":"cc.Size","width":720,"height":1280},"_anchorPoint":{"__type__":"cc.Vec2","x":0.5},"_trs":{"__type__":"TypedArray","ctor":"Float64Array","array":[0,-640,0,0,0,0,1,1,1,1]},"_zIndex":0},{"__type__":"cc.Node","_name":"GearBar","_parent":{"__id__":88},"_children":[{"__id__":90},{"__id__":91},{"__id__":171},{"__id__":179}],"_components":[{"__id__":180},{"__type__":"cc.Widget","node":{"__id__":89},"alignMode":0,"_alignFlags":45},{"__type__":"cc.Animation","node":{"__id__":89},"_clips":[{"__uuid__":"8d5naZ52hLV79rBgRV3GaV"}]}],"_prefab":{"__type__":"cc.PrefabInfo","root":{"__id__":89},"asset":{"__uuid__":"0f8pKVU3ZK/pE1BlnxmB7s"},"fileId":"a5MctsR1RCFpl+aRApRPs/"},"_contentSize":{"__type__":"cc.Size","width":720,"height":1280},"_trs":{"__type__":"TypedArray","ctor":"Float64Array","array":[0,640,0,0,0,0,1,1,1,1]},"_zIndex":0},{"__type__":"cc.Node","_name":"FallDownLayer","_parent":{"__id__":89},"_components":[{"__type__":"cc.Widget","node":{"__id__":90},"alignMode":0,"_alignFlags":45}],"_prefab":{"__type__":"cc.PrefabInfo","root":{"__id__":89},"asset":{"__uuid__":"0f8pKVU3ZK/pE1BlnxmB7s"},"fileId":"22XCdckQdA9La3crTRVJCG"},"_contentSize":{"__type__":"cc.Size","width":720,"height":1280},"_trs":{"__type__":"TypedArray","ctor":"Float64Array","array":[0,0,0,0,0,0,1,1,1,1]},"_zIndex":0},{"__type__":"cc.Node","_name":"GearFrame","_parent":{"__id__":89},"_children":[{"__id__":92}],"_components":[{"__type__":"cc.Widget","node":{"__id__":91},"alignMode":0,"_alignFlags":44,"_originalWidth":720}],"_prefab":{"__type__":"cc.PrefabInfo","root":{"__id__":89},"asset":{"__uuid__":"0f8pKVU3ZK/pE1BlnxmB7s"},"fileId":"302Km4H2JBu6yoCaBYuOw2"},"_contentSize":{"__type__":"cc.Size","width":720,"height":150},"_trs":{"__type__":"TypedArray","ctor":"Float64Array","array":[0,-565,0,0,0,0,1,1,1,1]},"_zIndex":0},{"__type__":"cc.Node","_name":"GearRoot","_parent":{"__id__":91},"_children":[{"__id__":93},{"__id__":95},{"__id__":96},{"__id__":97},{"__id__":121},{"__id__":145},{"__id__":169}],"_components":[{"__type__":"cc.Sprite","node":{"__id__":92}}],"_prefab":{"__type__":"cc.PrefabInfo","root":{"__id__":89},"asset":{"__uuid__":"0f8pKVU3ZK/pE1BlnxmB7s"},"fileId":"521M6Wp6ROEoRyIYJhyJFY"},"_contentSize":{"__type__":"cc.Size","width":711,"height":410},"_anchorPoint":{"__type__":"cc.Vec2","x":0.5,"y":0.75},"_trs":{"__type__":"TypedArray","ctor":"Float64Array","array":[0,0,0,0,0,0,1,1,1,1]},"_zIndex":0},{"__type__":"cc.Node","_name":"fallDownButton","_parent":{"__id__":92},"_children":[{"__id__":94}],"_components":[{"__type__":"cc.Sprite","node":{"__id__":93},"_spriteFrame":{"__uuid__":"49px9K7K1DMr3/EdT3q18h"}},{"__type__":"cc.Widget","node":{"__id__":93},"alignMode":0,"_alignFlags":4,"_bottom":397.90000000000003}],"_prefab":{"__type__":"cc.PrefabInfo","root":{"__id__":89},"asset":{"__uuid__":"0f8pKVU3ZK/pE1BlnxmB7s"},"fileId":"9aZlDv8S1Pd7kxlQ0+HNHS"},"_contentSize":{"__type__":"cc.Size","width":122,"height":36},"_trs":{"__type__":"TypedArray","ctor":"Float64Array","array":[0,108.40000000000003,0,0,0,0,1,1,1,1]},"_zIndex":0},{"__type__":"cc.Node","_name":"match_draw_button_up","_parent":{"__id__":93},"_components":[{"__type__":"cc.Sprite","node":{"__id__":94},"_spriteFrame":{"__uuid__":"ddXNcEbaVNh6wcCckrjmtv"}}],"_prefab":{"__type__":"cc.PrefabInfo","root":{"__id__":89},"asset":{"__uuid__":"0f8pKVU3ZK/pE1BlnxmB7s"},"fileId":"fab2V5QoZM/Lluj99ixRrK"},"_contentSize":{"__type__":"cc.Size","width":29,"height":14},"_trs":{"__type__":"TypedArray","ctor":"Float64Array","array":[0,0,0,0,0,0,1,1,1,1]},"_zIndex":0},{"__type__":"cc.Node","_name":"FrameBG","_parent":{"__id__":92},"_components":[{"__type__":"cc.Sprite","node":{"__id__":95},"_spriteFrame":{"__uuid__":"0flCcgsyRLRJA1y3/VAHKA"}}],"_prefab":{"__type__":"cc.PrefabInfo","root":{"__id__":89},"asset":{"__uuid__":"0f8pKVU3ZK/pE1BlnxmB7s"},"fileId":"9dVB0HW8NEqYu+FKGQkqCU"},"_contentSize":{"__type__":"cc.Size","width":711,"height":480},"_anchorPoint":{"__type__":"cc.Vec2","x":0.5,"y":0.787},"_trs":{"__type__":"TypedArray","ctor":"Float64Array","array":[0,0,0,0,0,0,1,1,1,1]},"_zIndex":0},{"__type__":"cc.Node","_name":"PauseButton","_parent":{"__id__":92},"_components":[{"__type__":"cc.Sprite","node":{"__id__":96},"_type":1,"_sizeMode":0,"_isTrimmedMode":false},{"__type__":"069c1FU/nxJ6YeuYJ8bTF9J","node":{"__id__":96},"pressedScale":1.05,"limitTouchTime":500}],"_prefab":{"__type__":"cc.PrefabInfo","root":{"__id__":89},"asset":{"__uuid__":"0f8pKVU3ZK/pE1BlnxmB7s"},"fileId":"b3WZDY3rxLyqiQJrOegDoQ"},"_contentSize":{"__type__":"cc.Size","width":72,"height":72},"_trs":{"__type__":"TypedArray","ctor":"Float64Array","array":[-271,-9,0,0,0,0,1,1,1,1]},"_zIndex":0},{"__type__":"cc.Node","_name":"Hammer","_parent":{"__id__":92},"_children":[{"__id__":98},{"__id__":119}],"_components":[{"__type__":"cc.Sprite","node":{"__id__":97},"_spriteFrame":{"__uuid__":"0aPb/zbZFCgqhI6j1X03JX"}},{"__type__":"c986awDkvdKZ4Y5F0cTOUwH","node":{"__id__":97},"amountFramePos1":{"__id__":99},"amountFramePos2":{"__id__":100},"itemRoot":{"__id__":98},"icon":{"__id__":102},"normalAmountRoot":{"__id__":107},"normalAmountFrame":{"__id__":108},"normalAmountLabel":{"__id__":110},"buyButton":{"__id__":111},"timeLimitedAmountRoot":{"__id__":112},"timeLimitedAmountFrame":{"__id__":116},"timeLimitedAmountLabel":{"__id__":118},"timeLimitedCountDownLabel":{"__id__":115},"lockButton":{"__id__":119},"lockIcon":{"__id__":119},"identifyComponent":{"__id__":120}},{"__id__":120},{"__type__":"cc.Animation","node":{"__id__":97},"_clips":[{"__uuid__":"88uwJuKP1Dt4e0zIzoGuvM"}]}],"_prefab":{"__type__":"cc.PrefabInfo","root":{"__id__":89},"asset":{"__uuid__":"0f8pKVU3ZK/pE1BlnxmB7s"},"fileId":"f9shhHXjpIj7uhvsDPFH96"},"_contentSize":{"__type__":"cc.Size","width":120,"height":125},"_trs":{"__type__":"TypedArray","ctor":"Float64Array","array":[-139,10,0,0,0,0,1,1,1,1]},"_zIndex":0},{"__type__":"cc.Node","_name":"itemFrame","_parent":{"__id__":97},"_children":[{"__id__":99},{"__id__":100},{"__id__":101},{"__id__":103},{"__id__":104},{"__id__":105},{"__id__":106},{"__id__":107},{"__id__":112}],"_prefab":{"__type__":"cc.PrefabInfo","root":{"__id__":89},"asset":{"__uuid__":"0f8pKVU3ZK/pE1BlnxmB7s"},"fileId":"04cfMVPXlCRIzdc8v2q9T+"},"_trs":{"__type__":"TypedArray","ctor":"Float64Array","array":[0,0,0,0,0,0,1,1,1,1]},"_zIndex":0},{"__type__":"cc.Node","_name":"amountPos1","_parent":{"__id__":98},"_prefab":{"__type__":"cc.PrefabInfo","root":{"__id__":89},"asset":{"__uuid__":"0f8pKVU3ZK/pE1BlnxmB7s"},"fileId":"20z8AJmzJBbYwarf9NPM8U"},"_trs":{"__type__":"TypedArray","ctor":"Float64Array","array":[50,1,0,0,0,0,1,0.75,0.75,1]},"_zIndex":0},{"__type__":"cc.Node","_name":"amountPos2","_parent":{"__id__":98},"_prefab":{"__type__":"cc.PrefabInfo","root":{"__id__":89},"asset":{"__uuid__":"0f8pKVU3ZK/pE1BlnxmB7s"},"fileId":"795lQ9SahJaIjw0/YtaRLB"},"_trs":{"__type__":"TypedArray","ctor":"Float64Array","array":[50,-40,0,0,0,0,1,0.75,0.75,1]},"_zIndex":0},{"__type__":"cc.Node","_name":"iconButton","_parent":{"__id__":98},"_components":[{"__id__":102},{"__type__":"069c1FU/nxJ6YeuYJ8bTF9J","node":{"__id__":101},"pressedScale":0.787,"limitTouchTime":500},{"__type__":"f41c7fUzppLL5BL0ZHlFDVT","node":{"__id__":101}}],"_prefab":{"__type__":"cc.PrefabInfo","root":{"__id__":89},"asset":{"__uuid__":"0f8pKVU3ZK/pE1BlnxmB7s"},"fileId":"82wOhvKdhCELmi2EWRIHE/"},"_contentSize":{"__type__":"cc.Size","width":117,"height":117},"_trs":{"__type__":"TypedArray","ctor":"Float64Array","array":[0,0,0,0,0,0,1,0.75,0.75,1]},"_zIndex":0},{"__type__":"cc.Sprite","node":{"__id__":101},"_spriteFrame":{"__uuid__":"75IOQwgelGhKIJzr5i4Hix"},"_sizeMode":2,"_isTrimmedMode":false},{"__type__":"cc.Node","_name":"match_frame_xing3","_parent":{"__id__":98},"_components":[{"__type__":"cc.Sprite","node":{"__id__":103},"_spriteFrame":{"__uuid__":"8c+UkF31hCUbz7+R/j85GB"}}],"_prefab":{"__type__":"cc.PrefabInfo","root":{"__id__":89},"asset":{"__uuid__":"0f8pKVU3ZK/pE1BlnxmB7s"},"fileId":"8a2c3UUCNO26gjqETzQIym"},"_opacity":0,"_contentSize":{"__type__":"cc.Size","width":38,"height":39},"_trs":{"__type__":"TypedArray","ctor":"Float64Array","array":[0,0,0,0,0,0,1,1,1,1]},"_zIndex":0},{"__type__":"cc.Node","_name":"match_frame_xing2","_parent":{"__id__":98},"_components":[{"__type__":"cc.Sprite","node":{"__id__":104},"_spriteFrame":{"__uuid__":"8c+UkF31hCUbz7+R/j85GB"}}],"_prefab":{"__type__":"cc.PrefabInfo","root":{"__id__":89},"asset":{"__uuid__":"0f8pKVU3ZK/pE1BlnxmB7s"},"fileId":"ef0N15DSpH06xkRr7rO+qA"},"_opacity":0,"_contentSize":{"__type__":"cc.Size","width":38,"height":39},"_trs":{"__type__":"TypedArray","ctor":"Float64Array","array":[0,0,0,0,0,0,1,1,1,1]},"_zIndex":0},{"__type__":"cc.Node","_name":"match_frame_xing1","_parent":{"__id__":98},"_components":[{"__type__":"cc.Sprite","node":{"__id__":105},"_spriteFrame":{"__uuid__":"8c+UkF31hCUbz7+R/j85GB"}}],"_prefab":{"__type__":"cc.PrefabInfo","root":{"__id__":89},"asset":{"__uuid__":"0f8pKVU3ZK/pE1BlnxmB7s"},"fileId":"8fsD9lwr9DFZt7Qlpp3Jlq"},"_opacity":0,"_contentSize":{"__type__":"cc.Size","width":38,"height":39},"_trs":{"__type__":"TypedArray","ctor":"Float64Array","array":[0,0,0,0,0,0,1,1,1,1]},"_zIndex":0},{"__type__":"cc.Node","_name":"match_frame_gearguang","_parent":{"__id__":98},"_components":[{"__type__":"cc.Sprite","node":{"__id__":106},"_spriteFrame":{"__uuid__":"f6M5aN4atDPb6ppdlv6wRW"}}],"_prefab":{"__type__":"cc.PrefabInfo","root":{"__id__":89},"asset":{"__uuid__":"0f8pKVU3ZK/pE1BlnxmB7s"},"fileId":"5fRA4WRDBGn6mUsU0dCiXg"},"_opacity":0,"_contentSize":{"__type__":"cc.Size","width":120,"height":125},"_trs":{"__type__":"TypedArray","ctor":"Float64Array","array":[0,0,0,0,0,0,1,1,1,1]},"_zIndex":0},{"__type__":"cc.Node","_name":"normalAmountFrame","_parent":{"__id__":98},"_children":[{"__id__":108}],"_prefab":{"__type__":"cc.PrefabInfo","root":{"__id__":89},"asset":{"__uuid__":"0f8pKVU3ZK/pE1BlnxmB7s"},"fileId":"b3mX6ZJedGvIiDhVt/L7IA"},"_trs":{"__type__":"TypedArray","ctor":"Float64Array","array":[0,0,0,0,0,0,1,1,1,1]},"_zIndex":0},{"__type__":"cc.Node","_name":"common_frame_amount","_parent":{"__id__":107},"_children":[{"__id__":109},{"__id__":111}],"_components":[{"__type__":"cc.Sprite","node":{"__id__":108},"_spriteFrame":{"__uuid__":"28VUNuO0ZAoYNqaY7uDtiV"},"_sizeMode":2,"_isTrimmedMode":false}],"_prefab":{"__type__":"cc.PrefabInfo","root":{"__id__":89},"asset":{"__uuid__":"0f8pKVU3ZK/pE1BlnxmB7s"},"fileId":"4b/FgPDEdBFojybGzNUYDH"},"_contentSize":{"__type__":"cc.Size","width":49,"height":52},"_trs":{"__type__":"TypedArray","ctor":"Float64Array","array":[50,1,0,0,0,0,1,0.75,0.75,1]},"_zIndex":0},{"__type__":"cc.Node","_name":"amountLabel","_parent":{"__id__":108},"_components":[{"__id__":110}],"_prefab":{"__type__":"cc.PrefabInfo","root":{"__id__":89},"asset":{"__uuid__":"0f8pKVU3ZK/pE1BlnxmB7s"},"fileId":"ceLWIG5x1JxYZqtwKv+n6D"},"_contentSize":{"__type__":"cc.Size","width":36,"height":21},"_trs":{"__type__":"TypedArray","ctor":"Float64Array","array":[0,2,0,0,0,0,1,1,1,1]},"_zIndex":0},{"__type__":"cc.Label","node":{"__id__":109},"_useOriginalSize":false,"_string":"99","_N$string":"99","_fontSize":32,"_lineHeight":21,"_N$file":{"__uuid__":"96/Cmi4OpC2IkOdTDlMLwZ"},"_isSystemFontUsed":false,"_N$horizontalAlign":1,"_N$verticalAlign":1},{"__type__":"cc.Node","_name":"buyButton","_parent":{"__id__":108},"_active":false,"_components":[{"__type__":"cc.Label","node":{"__id__":111},"_useOriginalSize":false,"_string":"+","_N$string":"+","_fontSize":50,"_lineHeight":18,"_N$file":{"__uuid__":"96/Cmi4OpC2IkOdTDlMLwZ"},"_isSystemFontUsed":false,"_N$horizontalAlign":1,"_N$verticalAlign":1},{"__type__":"069c1FU/nxJ6YeuYJ8bTF9J","node":{"__id__":111},"pressedScale":1.05,"limitTouchTime":500}],"_prefab":{"__type__":"cc.PrefabInfo","root":{"__id__":89},"asset":{"__uuid__":"0f8pKVU3ZK/pE1BlnxmB7s"},"fileId":"6eWKZTrhNJA5af8KoZ+pYT"},"_contentSize":{"__type__":"cc.Size","width":26.56,"height":28.13},"_trs":{"__type__":"TypedArray","ctor":"Float64Array","array":[0,0,0,0,0,0,1,1,1,1]},"_zIndex":0},{"__type__":"cc.Node","_name":"timeLimitedAmountFrame","_parent":{"__id__":98},"_children":[{"__id__":113},{"__id__":116}],"_prefab":{"__type__":"cc.PrefabInfo","root":{"__id__":89},"asset":{"__uuid__":"0f8pKVU3ZK/pE1BlnxmB7s"},"fileId":"11lwd/mU5G24laGxwjslYj"},"_trs":{"__type__":"TypedArray","ctor":"Float64Array","array":[0,0,0,0,0,0,1,1,1,1]},"_zIndex":0},{"__type__":"cc.Node","_name":"match_gear_clock_bg","_parent":{"__id__":112},"_children":[{"__id__":114}],"_components":[{"__type__":"cc.Sprite","node":{"__id__":113},"_spriteFrame":{"__uuid__":"37W718CjVNGJ4ztgSIRf6j"},"_type":1,"_sizeMode":0}],"_prefab":{"__type__":"cc.PrefabInfo","root":{"__id__":89},"asset":{"__uuid__":"0f8pKVU3ZK/pE1BlnxmB7s"},"fileId":"0e7g4VI3NCh4LNKp6Zjx2k"},"_contentSize":{"__type__":"cc.Size","width":75,"height":26},"_trs":{"__type__":"TypedArray","ctor":"Float64Array","array":[-17.1,-46.1,0,0,0,0,1,1,1,1]},"_zIndex":0},{"__type__":"cc.Node","_name":"label","_parent":{"__id__":113},"_components":[{"__id__":115},{"__type__":"cc.LabelOutline","node":{"__id__":114},"_color":{"__type__":"cc.Color","r":39,"g":175,"b":49},"_width":1.5}],"_prefab":{"__type__":"cc.PrefabInfo","root":{"__id__":89},"asset":{"__uuid__":"0f8pKVU3ZK/pE1BlnxmB7s"},"fileId":"41BIFmihNIgob0XUl1c18d"},"_contentSize":{"__type__":"cc.Size","width":54,"height":20},"_trs":{"__type__":"TypedArray","ctor":"Float64Array","array":[0,1.2,0,0,0,0,1,1,1,1]},"_zIndex":0},{"__type__":"cc.Label","node":{"__id__":114},"_srcBlendFactor":1,"_useOriginalSize":false,"_string":"00:00:23","_N$string":"00:00:23","_fontSize":12,"_lineHeight":16,"_enableWrapText":false,"_N$horizontalAlign":1,"_N$verticalAlign":1,"_N$overflow":2},{"__type__":"cc.Node","_name":"common_frame_amount","_parent":{"__id__":112},"_children":[{"__id__":117}],"_components":[{"__type__":"cc.Sprite","node":{"__id__":116},"_spriteFrame":{"__uuid__":"c6eTEZj5BMNJNpHnILwXXo"},"_sizeMode":2,"_isTrimmedMode":false}],"_prefab":{"__type__":"cc.PrefabInfo","root":{"__id__":89},"asset":{"__uuid__":"0f8pKVU3ZK/pE1BlnxmB7s"},"fileId":"21DnjT5OFJ8ZN7q2ztM2Pm"},"_contentSize":{"__type__":"cc.Size","width":66,"height":70},"_trs":{"__type__":"TypedArray","ctor":"Float64Array","array":[50,-40,0,0,0,0,1,0.75,0.75,1]},"_zIndex":0},{"__type__":"cc.Node","_name":"amountLabel","_parent":{"__id__":116},"_components":[{"__id__":118}],"_prefab":{"__type__":"cc.PrefabInfo","root":{"__id__":89},"asset":{"__uuid__":"0f8pKVU3ZK/pE1BlnxmB7s"},"fileId":"9cQsXpwQhA4LJApSnYpv3N"},"_contentSize":{"__type__":"cc.Size","width":39.5,"height":23.63},"_trs":{"__type__":"TypedArray","ctor":"Float64Array","array":[0,3,0,0,0,0,1,1,1,1]},"_zIndex":0},{"__type__":"cc.Label","node":{"__id__":117},"_useOriginalSize":false,"_string":"99","_N$string":"99","_fontSize":36,"_lineHeight":21,"_N$file":{"__uuid__":"96/Cmi4OpC2IkOdTDlMLwZ"},"_isSystemFontUsed":false,"_spacingX":-1,"_N$horizontalAlign":1,"_N$verticalAlign":1},{"__type__":"cc.Node","_name":"lockIcon","_parent":{"__id__":97},"_components":[{"__type__":"cc.Sprite","node":{"__id__":119},"_spriteFrame":{"__uuid__":"9cFmNJcn1Hb5r5Y629iJ5M"}},{"__type__":"069c1FU/nxJ6YeuYJ8bTF9J","node":{"__id__":119},"limitTouchTime":500}],"_prefab":{"__type__":"cc.PrefabInfo","root":{"__id__":89},"asset":{"__uuid__":"0f8pKVU3ZK/pE1BlnxmB7s"},"fileId":"e9UlUGhoREMKW1+uZwDlTs"},"_contentSize":{"__type__":"cc.Size","width":57,"height":74},"_trs":{"__type__":"TypedArray","ctor":"Float64Array","array":[0,0,0,0,0,0,1,1,1,1]},"_zIndex":0},{"__type__":"27f1ez202tMP7oxJ80RscXS","node":{"__id__":97}},{"__type__":"cc.Node","_name":"Bomb","_parent":{"__id__":92},"_children":[{"__id__":122},{"__id__":143}],"_components":[{"__type__":"cc.Sprite","node":{"__id__":121},"_spriteFrame":{"__uuid__":"0aPb/zbZFCgqhI6j1X03JX"}},{"__type__":"c986awDkvdKZ4Y5F0cTOUwH","node":{"__id__":121},"amountFramePos1":{"__id__":123},"amountFramePos2":{"__id__":124},"itemRoot":{"__id__":122},"icon":{"__id__":126},"normalAmountRoot":{"__id__":131},"normalAmountFrame":{"__id__":132},"normalAmountLabel":{"__id__":134},"buyButton":{"__id__":135},"timeLimitedAmountRoot":{"__id__":136},"timeLimitedAmountFrame":{"__id__":140},"timeLimitedAmountLabel":{"__id__":142},"timeLimitedCountDownLabel":{"__id__":139},"lockButton":{"__id__":143},"lockIcon":{"__id__":143},"identifyComponent":{"__id__":144}},{"__id__":144},{"__type__":"cc.Animation","node":{"__id__":121},"_clips":[{"__uuid__":"88uwJuKP1Dt4e0zIzoGuvM"}]}],"_prefab":{"__type__":"cc.PrefabInfo","root":{"__id__":89},"asset":{"__uuid__":"0f8pKVU3ZK/pE1BlnxmB7s"},"fileId":"8a7TVLPXlPHJ8uc66RUxay"},"_contentSize":{"__type__":"cc.Size","width":120,"height":125},"_trs":{"__type__":"TypedArray","ctor":"Float64Array","array":[43,10,0,0,0,0,1,1,1,1]},"_zIndex":0},{"__type__":"cc.Node","_name":"itemFrame","_parent":{"__id__":121},"_children":[{"__id__":123},{"__id__":124},{"__id__":125},{"__id__":127},{"__id__":128},{"__id__":129},{"__id__":130},{"__id__":131},{"__id__":136}],"_prefab":{"__type__":"cc.PrefabInfo","root":{"__id__":89},"asset":{"__uuid__":"0f8pKVU3ZK/pE1BlnxmB7s"},"fileId":"5cuUzGz7lGkbKSRtutClJZ"},"_trs":{"__type__":"TypedArray","ctor":"Float64Array","array":[0,0,0,0,0,0,1,1,1,1]},"_zIndex":0},{"__type__":"cc.Node","_name":"amountPos1","_parent":{"__id__":122},"_prefab":{"__type__":"cc.PrefabInfo","root":{"__id__":89},"asset":{"__uuid__":"0f8pKVU3ZK/pE1BlnxmB7s"},"fileId":"7ahO7rFDNKo48b/p7+FnWD"},"_trs":{"__type__":"TypedArray","ctor":"Float64Array","array":[50,1,0,0,0,0,1,0.75,0.75,1]},"_zIndex":0},{"__type__":"cc.Node","_name":"amountPos2","_parent":{"__id__":122},"_prefab":{"__type__":"cc.PrefabInfo","root":{"__id__":89},"asset":{"__uuid__":"0f8pKVU3ZK/pE1BlnxmB7s"},"fileId":"f1GSrTEhlGNJKelIxJ7g+i"},"_trs":{"__type__":"TypedArray","ctor":"Float64Array","array":[50,-40,0,0,0,0,1,0.75,0.75,1]},"_zIndex":0},{"__type__":"cc.Node","_name":"iconButton","_parent":{"__id__":122},"_components":[{"__id__":126},{"__type__":"069c1FU/nxJ6YeuYJ8bTF9J","node":{"__id__":125},"pressedScale":0.787,"limitTouchTime":500},{"__type__":"f41c7fUzppLL5BL0ZHlFDVT","node":{"__id__":125}}],"_prefab":{"__type__":"cc.PrefabInfo","root":{"__id__":89},"asset":{"__uuid__":"0f8pKVU3ZK/pE1BlnxmB7s"},"fileId":"87p/lE3HRDjrEarr7AaVS3"},"_contentSize":{"__type__":"cc.Size","width":117,"height":117},"_trs":{"__type__":"TypedArray","ctor":"Float64Array","array":[0,0,0,0,0,0,1,0.75,0.75,1]},"_zIndex":0},{"__type__":"cc.Sprite","node":{"__id__":125},"_spriteFrame":{"__uuid__":"75IOQwgelGhKIJzr5i4Hix"},"_sizeMode":2,"_isTrimmedMode":false},{"__type__":"cc.Node","_name":"match_frame_xing3","_parent":{"__id__":122},"_components":[{"__type__":"cc.Sprite","node":{"__id__":127},"_spriteFrame":{"__uuid__":"8c+UkF31hCUbz7+R/j85GB"}}],"_prefab":{"__type__":"cc.PrefabInfo","root":{"__id__":89},"asset":{"__uuid__":"0f8pKVU3ZK/pE1BlnxmB7s"},"fileId":"c3pP9lvfxMUY+3UboZL0ks"},"_opacity":0,"_contentSize":{"__type__":"cc.Size","width":38,"height":39},"_trs":{"__type__":"TypedArray","ctor":"Float64Array","array":[0,0,0,0,0,0,1,1,1,1]},"_zIndex":0},{"__type__":"cc.Node","_name":"match_frame_xing2","_parent":{"__id__":122},"_components":[{"__type__":"cc.Sprite","node":{"__id__":128},"_spriteFrame":{"__uuid__":"8c+UkF31hCUbz7+R/j85GB"}}],"_prefab":{"__type__":"cc.PrefabInfo","root":{"__id__":89},"asset":{"__uuid__":"0f8pKVU3ZK/pE1BlnxmB7s"},"fileId":"55foGlGT5Jvr7Lv5YSohy6"},"_opacity":0,"_contentSize":{"__type__":"cc.Size","width":38,"height":39},"_trs":{"__type__":"TypedArray","ctor":"Float64Array","array":[0,0,0,0,0,0,1,1,1,1]},"_zIndex":0},{"__type__":"cc.Node","_name":"match_frame_xing1","_parent":{"__id__":122},"_components":[{"__type__":"cc.Sprite","node":{"__id__":129},"_spriteFrame":{"__uuid__":"8c+UkF31hCUbz7+R/j85GB"}}],"_prefab":{"__type__":"cc.PrefabInfo","root":{"__id__":89},"asset":{"__uuid__":"0f8pKVU3ZK/pE1BlnxmB7s"},"fileId":"b8YxwWvxRBoKNrsTFiR3yk"},"_opacity":0,"_contentSize":{"__type__":"cc.Size","width":38,"height":39},"_trs":{"__type__":"TypedArray","ctor":"Float64Array","array":[0,0,0,0,0,0,1,1,1,1]},"_zIndex":0},{"__type__":"cc.Node","_name":"match_frame_gearguang","_parent":{"__id__":122},"_components":[{"__type__":"cc.Sprite","node":{"__id__":130},"_spriteFrame":{"__uuid__":"f6M5aN4atDPb6ppdlv6wRW"}}],"_prefab":{"__type__":"cc.PrefabInfo","root":{"__id__":89},"asset":{"__uuid__":"0f8pKVU3ZK/pE1BlnxmB7s"},"fileId":"37EATl0cRFpYUlBjS7r31G"},"_opacity":0,"_contentSize":{"__type__":"cc.Size","width":120,"height":125},"_trs":{"__type__":"TypedArray","ctor":"Float64Array","array":[0,0,0,0,0,0,1,1,1,1]},"_zIndex":0},{"__type__":"cc.Node","_name":"normalAmountFrame","_parent":{"__id__":122},"_children":[{"__id__":132}],"_prefab":{"__type__":"cc.PrefabInfo","root":{"__id__":89},"asset":{"__uuid__":"0f8pKVU3ZK/pE1BlnxmB7s"},"fileId":"b26GlNDyRBaotWVMtWM6PV"},"_trs":{"__type__":"TypedArray","ctor":"Float64Array","array":[0,0,0,0,0,0,1,1,1,1]},"_zIndex":0},{"__type__":"cc.Node","_name":"common_frame_amount","_parent":{"__id__":131},"_children":[{"__id__":133},{"__id__":135}],"_components":[{"__type__":"cc.Sprite","node":{"__id__":132},"_spriteFrame":{"__uuid__":"28VUNuO0ZAoYNqaY7uDtiV"},"_sizeMode":2,"_isTrimmedMode":false}],"_prefab":{"__type__":"cc.PrefabInfo","root":{"__id__":89},"asset":{"__uuid__":"0f8pKVU3ZK/pE1BlnxmB7s"},"fileId":"d0J1i6psVPTIBzbX1wyCGi"},"_contentSize":{"__type__":"cc.Size","width":49,"height":52},"_trs":{"__type__":"TypedArray","ctor":"Float64Array","array":[50,1,0,0,0,0,1,0.75,0.75,1]},"_zIndex":0},{"__type__":"cc.Node","_name":"amountLabel","_parent":{"__id__":132},"_components":[{"__id__":134}],"_prefab":{"__type__":"cc.PrefabInfo","root":{"__id__":89},"asset":{"__uuid__":"0f8pKVU3ZK/pE1BlnxmB7s"},"fileId":"6eKPhIRKJAhZA8gy2DWQE/"},"_contentSize":{"__type__":"cc.Size","width":36,"height":21},"_trs":{"__type__":"TypedArray","ctor":"Float64Array","array":[0,2,0,0,0,0,1,1,1,1]},"_zIndex":0},{"__type__":"cc.Label","node":{"__id__":133},"_useOriginalSize":false,"_string":"99","_N$string":"99","_fontSize":32,"_lineHeight":21,"_N$file":{"__uuid__":"96/Cmi4OpC2IkOdTDlMLwZ"},"_isSystemFontUsed":false,"_N$horizontalAlign":1,"_N$verticalAlign":1},{"__type__":"cc.Node","_name":"buyButton","_parent":{"__id__":132},"_active":false,"_components":[{"__type__":"cc.Label","node":{"__id__":135},"_useOriginalSize":false,"_string":"+","_N$string":"+","_fontSize":50,"_lineHeight":18,"_N$file":{"__uuid__":"96/Cmi4OpC2IkOdTDlMLwZ"},"_isSystemFontUsed":false,"_N$horizontalAlign":1,"_N$verticalAlign":1},{"__type__":"069c1FU/nxJ6YeuYJ8bTF9J","node":{"__id__":135},"pressedScale":1.05,"limitTouchTime":500}],"_prefab":{"__type__":"cc.PrefabInfo","root":{"__id__":89},"asset":{"__uuid__":"0f8pKVU3ZK/pE1BlnxmB7s"},"fileId":"fcP2O0tNJM8ZsAAfTzV4vr"},"_contentSize":{"__type__":"cc.Size","width":26.56,"height":28.13},"_trs":{"__type__":"TypedArray","ctor":"Float64Array","array":[0,0,0,0,0,0,1,1,1,1]},"_zIndex":0},{"__type__":"cc.Node","_name":"timeLimitedAmountFrame","_parent":{"__id__":122},"_children":[{"__id__":137},{"__id__":140}],"_prefab":{"__type__":"cc.PrefabInfo","root":{"__id__":89},"asset":{"__uuid__":"0f8pKVU3ZK/pE1BlnxmB7s"},"fileId":"9aA8I/0URFPaic+4fGkQpA"},"_trs":{"__type__":"TypedArray","ctor":"Float64Array","array":[0,0,0,0,0,0,1,1,1,1]},"_zIndex":0},{"__type__":"cc.Node","_name":"match_gear_clock_bg","_parent":{"__id__":136},"_children":[{"__id__":138}],"_components":[{"__type__":"cc.Sprite","node":{"__id__":137},"_spriteFrame":{"__uuid__":"37W718CjVNGJ4ztgSIRf6j"},"_type":1,"_sizeMode":0}],"_prefab":{"__type__":"cc.PrefabInfo","root":{"__id__":89},"asset":{"__uuid__":"0f8pKVU3ZK/pE1BlnxmB7s"},"fileId":"38UVnCXm9BsK0Y9hpu1UHX"},"_contentSize":{"__type__":"cc.Size","width":75,"height":26},"_trs":{"__type__":"TypedArray","ctor":"Float64Array","array":[-17.1,-46.1,0,0,0,0,1,1,1,1]},"_zIndex":0},{"__type__":"cc.Node","_name":"label","_parent":{"__id__":137},"_components":[{"__id__":139},{"__type__":"cc.LabelOutline","node":{"__id__":138},"_color":{"__type__":"cc.Color","r":39,"g":175,"b":49},"_width":1.5}],"_prefab":{"__type__":"cc.PrefabInfo","root":{"__id__":89},"asset":{"__uuid__":"0f8pKVU3ZK/pE1BlnxmB7s"},"fileId":"95JJD+Y4pGZKndyEoP9rjV"},"_contentSize":{"__type__":"cc.Size","width":54,"height":20},"_trs":{"__type__":"TypedArray","ctor":"Float64Array","array":[0,1.2,0,0,0,0,1,1,1,1]},"_zIndex":0},{"__type__":"cc.Label","node":{"__id__":138},"_srcBlendFactor":1,"_useOriginalSize":false,"_string":"00:00:23","_N$string":"00:00:23","_fontSize":12,"_lineHeight":16,"_enableWrapText":false,"_N$horizontalAlign":1,"_N$verticalAlign":1,"_N$overflow":2},{"__type__":"cc.Node","_name":"common_frame_amount","_parent":{"__id__":136},"_children":[{"__id__":141}],"_components":[{"__type__":"cc.Sprite","node":{"__id__":140},"_spriteFrame":{"__uuid__":"c6eTEZj5BMNJNpHnILwXXo"},"_sizeMode":2,"_isTrimmedMode":false}],"_prefab":{"__type__":"cc.PrefabInfo","root":{"__id__":89},"asset":{"__uuid__":"0f8pKVU3ZK/pE1BlnxmB7s"},"fileId":"7dtFtW6I9APLT2PU7+hkqm"},"_contentSize":{"__type__":"cc.Size","width":66,"height":70},"_trs":{"__type__":"TypedArray","ctor":"Float64Array","array":[50,-40,0,0,0,0,1,0.75,0.75,1]},"_zIndex":0},{"__type__":"cc.Node","_name":"amountLabel","_parent":{"__id__":140},"_components":[{"__id__":142}],"_prefab":{"__type__":"cc.PrefabInfo","root":{"__id__":89},"asset":{"__uuid__":"0f8pKVU3ZK/pE1BlnxmB7s"},"fileId":"f5vCtoWmpKFoqvj812EP+R"},"_contentSize":{"__type__":"cc.Size","width":39.5,"height":23.63},"_trs":{"__type__":"TypedArray","ctor":"Float64Array","array":[0,3,0,0,0,0,1,1,1,1]},"_zIndex":0},{"__type__":"cc.Label","node":{"__id__":141},"_useOriginalSize":false,"_string":"99","_N$string":"99","_fontSize":36,"_lineHeight":21,"_N$file":{"__uuid__":"96/Cmi4OpC2IkOdTDlMLwZ"},"_isSystemFontUsed":false,"_spacingX":-1,"_N$horizontalAlign":1,"_N$verticalAlign":1},{"__type__":"cc.Node","_name":"lockIcon","_parent":{"__id__":121},"_components":[{"__type__":"cc.Sprite","node":{"__id__":143},"_spriteFrame":{"__uuid__":"9cFmNJcn1Hb5r5Y629iJ5M"}},{"__type__":"069c1FU/nxJ6YeuYJ8bTF9J","node":{"__id__":143},"limitTouchTime":500}],"_prefab":{"__type__":"cc.PrefabInfo","root":{"__id__":89},"asset":{"__uuid__":"0f8pKVU3ZK/pE1BlnxmB7s"},"fileId":"55TZTSLaJGQ7tJ3o4MYagZ"},"_contentSize":{"__type__":"cc.Size","width":57,"height":74},"_trs":{"__type__":"TypedArray","ctor":"Float64Array","array":[0,0,0,0,0,0,1,1,1,1]},"_zIndex":0},{"__type__":"27f1ez202tMP7oxJ80RscXS","node":{"__id__":121}},{"__type__":"cc.Node","_name":"Swap","_parent":{"__id__":92},"_children":[{"__id__":146},{"__id__":167}],"_components":[{"__type__":"cc.Sprite","node":{"__id__":145},"_spriteFrame":{"__uuid__":"0aPb/zbZFCgqhI6j1X03JX"}},{"__type__":"c986awDkvdKZ4Y5F0cTOUwH","node":{"__id__":145},"amountFramePos1":{"__id__":147},"amountFramePos2":{"__id__":148},"itemRoot":{"__id__":146},"icon":{"__id__":150},"normalAmountRoot":{"__id__":155},"normalAmountFrame":{"__id__":156},"normalAmountLabel":{"__id__":158},"buyButton":{"__id__":159},"timeLimitedAmountRoot":{"__id__":160},"timeLimitedAmountFrame":{"__id__":164},"timeLimitedAmountLabel":{"__id__":166},"timeLimitedCountDownLabel":{"__id__":163},"lockButton":{"__id__":167},"lockIcon":{"__id__":167},"identifyComponent":{"__id__":168}},{"__id__":168},{"__type__":"cc.Animation","node":{"__id__":145},"_clips":[{"__uuid__":"88uwJuKP1Dt4e0zIzoGuvM"}]}],"_prefab":{"__type__":"cc.PrefabInfo","root":{"__id__":89},"asset":{"__uuid__":"0f8pKVU3ZK/pE1BlnxmB7s"},"fileId":"71StJju/tKoqAQhkas0skb"},"_contentSize":{"__type__":"cc.Size","width":120,"height":125},"_trs":{"__type__":"TypedArray","ctor":"Float64Array","array":[224,10,0,0,0,0,1,1,1,1]},"_zIndex":0},{"__type__":"cc.Node","_name":"itemFrame","_parent":{"__id__":145},"_children":[{"__id__":147},{"__id__":148},{"__id__":149},{"__id__":151},{"__id__":152},{"__id__":153},{"__id__":154},{"__id__":155},{"__id__":160}],"_prefab":{"__type__":"cc.PrefabInfo","root":{"__id__":89},"asset":{"__uuid__":"0f8pKVU3ZK/pE1BlnxmB7s"},"fileId":"e3QFYGxFRNboKLvJ+EpLP5"},"_trs":{"__type__":"TypedArray","ctor":"Float64Array","array":[0,0,0,0,0,0,1,1,1,1]},"_zIndex":0},{"__type__":"cc.Node","_name":"amountPos1","_parent":{"__id__":146},"_prefab":{"__type__":"cc.PrefabInfo","root":{"__id__":89},"asset":{"__uuid__":"0f8pKVU3ZK/pE1BlnxmB7s"},"fileId":"94sdMicxxB4pcneEjsQhhs"},"_trs":{"__type__":"TypedArray","ctor":"Float64Array","array":[50,1,0,0,0,0,1,0.75,0.75,1]},"_zIndex":0},{"__type__":"cc.Node","_name":"amountPos2","_parent":{"__id__":146},"_prefab":{"__type__":"cc.PrefabInfo","root":{"__id__":89},"asset":{"__uuid__":"0f8pKVU3ZK/pE1BlnxmB7s"},"fileId":"acNS0alU9AT5YVBVjzVCDM"},"_trs":{"__type__":"TypedArray","ctor":"Float64Array","array":[50,-40,0,0,0,0,1,0.75,0.75,1]},"_zIndex":0},{"__type__":"cc.Node","_name":"iconButton","_parent":{"__id__":146},"_components":[{"__id__":150},{"__type__":"069c1FU/nxJ6YeuYJ8bTF9J","node":{"__id__":149},"pressedScale":0.787,"limitTouchTime":500},{"__type__":"f41c7fUzppLL5BL0ZHlFDVT","node":{"__id__":149}}],"_prefab":{"__type__":"cc.PrefabInfo","root":{"__id__":89},"asset":{"__uuid__":"0f8pKVU3ZK/pE1BlnxmB7s"},"fileId":"3egOdaWyFH4r+Q+t8UWdST"},"_contentSize":{"__type__":"cc.Size","width":117,"height":117},"_trs":{"__type__":"TypedArray","ctor":"Float64Array","array":[0,0,0,0,0,0,1,0.75,0.75,1]},"_zIndex":0},{"__type__":"cc.Sprite","node":{"__id__":149},"_spriteFrame":{"__uuid__":"75IOQwgelGhKIJzr5i4Hix"},"_sizeMode":2,"_isTrimmedMode":false},{"__type__":"cc.Node","_name":"match_frame_xing3","_parent":{"__id__":146},"_components":[{"__type__":"cc.Sprite","node":{"__id__":151},"_spriteFrame":{"__uuid__":"8c+UkF31hCUbz7+R/j85GB"}}],"_prefab":{"__type__":"cc.PrefabInfo","root":{"__id__":89},"asset":{"__uuid__":"0f8pKVU3ZK/pE1BlnxmB7s"},"fileId":"9cQ8RVqxdG/JRrH2LSEciV"},"_opacity":0,"_contentSize":{"__type__":"cc.Size","width":38,"height":39},"_trs":{"__type__":"TypedArray","ctor":"Float64Array","array":[0,0,0,0,0,0,1,1,1,1]},"_zIndex":0},{"__type__":"cc.Node","_name":"match_frame_xing2","_parent":{"__id__":146},"_components":[{"__type__":"cc.Sprite","node":{"__id__":152},"_spriteFrame":{"__uuid__":"8c+UkF31hCUbz7+R/j85GB"}}],"_prefab":{"__type__":"cc.PrefabInfo","root":{"__id__":89},"asset":{"__uuid__":"0f8pKVU3ZK/pE1BlnxmB7s"},"fileId":"5aJq1zX0VHCbBIuNk6gz94"},"_opacity":0,"_contentSize":{"__type__":"cc.Size","width":38,"height":39},"_trs":{"__type__":"TypedArray","ctor":"Float64Array","array":[0,0,0,0,0,0,1,1,1,1]},"_zIndex":0},{"__type__":"cc.Node","_name":"match_frame_xing1","_parent":{"__id__":146},"_components":[{"__type__":"cc.Sprite","node":{"__id__":153},"_spriteFrame":{"__uuid__":"8c+UkF31hCUbz7+R/j85GB"}}],"_prefab":{"__type__":"cc.PrefabInfo","root":{"__id__":89},"asset":{"__uuid__":"0f8pKVU3ZK/pE1BlnxmB7s"},"fileId":"bdqzWlWCFO5acfKiPqN/As"},"_opacity":0,"_contentSize":{"__type__":"cc.Size","width":38,"height":39},"_trs":{"__type__":"TypedArray","ctor":"Float64Array","array":[0,0,0,0,0,0,1,1,1,1]},"_zIndex":0},{"__type__":"cc.Node","_name":"match_frame_gearguang","_parent":{"__id__":146},"_components":[{"__type__":"cc.Sprite","node":{"__id__":154},"_spriteFrame":{"__uuid__":"f6M5aN4atDPb6ppdlv6wRW"}}],"_prefab":{"__type__":"cc.PrefabInfo","root":{"__id__":89},"asset":{"__uuid__":"0f8pKVU3ZK/pE1BlnxmB7s"},"fileId":"56Uu+a3I9JALjOE7LYZrTq"},"_opacity":0,"_contentSize":{"__type__":"cc.Size","width":120,"height":125},"_trs":{"__type__":"TypedArray","ctor":"Float64Array","array":[0,0,0,0,0,0,1,1,1,1]},"_zIndex":0},{"__type__":"cc.Node","_name":"normalAmountFrame","_parent":{"__id__":146},"_children":[{"__id__":156}],"_prefab":{"__type__":"cc.PrefabInfo","root":{"__id__":89},"asset":{"__uuid__":"0f8pKVU3ZK/pE1BlnxmB7s"},"fileId":"409GOHiKNPPIkchX8xLIRK"},"_trs":{"__type__":"TypedArray","ctor":"Float64Array","array":[0,0,0,0,0,0,1,1,1,1]},"_zIndex":0},{"__type__":"cc.Node","_name":"common_frame_amount","_parent":{"__id__":155},"_children":[{"__id__":157},{"__id__":159}],"_components":[{"__type__":"cc.Sprite","node":{"__id__":156},"_spriteFrame":{"__uuid__":"28VUNuO0ZAoYNqaY7uDtiV"},"_sizeMode":2,"_isTrimmedMode":false}],"_prefab":{"__type__":"cc.PrefabInfo","root":{"__id__":89},"asset":{"__uuid__":"0f8pKVU3ZK/pE1BlnxmB7s"},"fileId":"0aDnAka25KGLRyw6W3GNsB"},"_contentSize":{"__type__":"cc.Size","width":49,"height":52},"_trs":{"__type__":"TypedArray","ctor":"Float64Array","array":[50,1,0,0,0,0,1,0.75,0.75,1]},"_zIndex":0},{"__type__":"cc.Node","_name":"amountLabel","_parent":{"__id__":156},"_components":[{"__id__":158}],"_prefab":{"__type__":"cc.PrefabInfo","root":{"__id__":89},"asset":{"__uuid__":"0f8pKVU3ZK/pE1BlnxmB7s"},"fileId":"41bL4JU/5DR54mnRJuN5g0"},"_contentSize":{"__type__":"cc.Size","width":36,"height":21},"_trs":{"__type__":"TypedArray","ctor":"Float64Array","array":[0,2,0,0,0,0,1,1,1,1]},"_zIndex":0},{"__type__":"cc.Label","node":{"__id__":157},"_useOriginalSize":false,"_string":"99","_N$string":"99","_fontSize":32,"_lineHeight":21,"_N$file":{"__uuid__":"96/Cmi4OpC2IkOdTDlMLwZ"},"_isSystemFontUsed":false,"_N$horizontalAlign":1,"_N$verticalAlign":1},{"__type__":"cc.Node","_name":"buyButton","_parent":{"__id__":156},"_active":false,"_components":[{"__type__":"cc.Label","node":{"__id__":159},"_useOriginalSize":false,"_string":"+","_N$string":"+","_fontSize":50,"_lineHeight":18,"_N$file":{"__uuid__":"96/Cmi4OpC2IkOdTDlMLwZ"},"_isSystemFontUsed":false,"_N$horizontalAlign":1,"_N$verticalAlign":1},{"__type__":"069c1FU/nxJ6YeuYJ8bTF9J","node":{"__id__":159},"pressedScale":1.05,"limitTouchTime":500}],"_prefab":{"__type__":"cc.PrefabInfo","root":{"__id__":89},"asset":{"__uuid__":"0f8pKVU3ZK/pE1BlnxmB7s"},"fileId":"1124DGqbZAY7pDN5S4b//4"},"_contentSize":{"__type__":"cc.Size","width":26.56,"height":28.13},"_trs":{"__type__":"TypedArray","ctor":"Float64Array","array":[0,0,0,0,0,0,1,1,1,1]},"_zIndex":0},{"__type__":"cc.Node","_name":"timeLimitedAmountFrame","_parent":{"__id__":146},"_children":[{"__id__":161},{"__id__":164}],"_prefab":{"__type__":"cc.PrefabInfo","root":{"__id__":89},"asset":{"__uuid__":"0f8pKVU3ZK/pE1BlnxmB7s"},"fileId":"81SHT37z5J8KDCCy6g14OA"},"_trs":{"__type__":"TypedArray","ctor":"Float64Array","array":[0,0,0,0,0,0,1,1,1,1]},"_zIndex":0},{"__type__":"cc.Node","_name":"match_gear_clock_bg","_parent":{"__id__":160},"_children":[{"__id__":162}],"_components":[{"__type__":"cc.Sprite","node":{"__id__":161},"_spriteFrame":{"__uuid__":"37W718CjVNGJ4ztgSIRf6j"},"_type":1,"_sizeMode":0}],"_prefab":{"__type__":"cc.PrefabInfo","root":{"__id__":89},"asset":{"__uuid__":"0f8pKVU3ZK/pE1BlnxmB7s"},"fileId":"47GDL3JrhJSLGrHYPtEy7m"},"_contentSize":{"__type__":"cc.Size","width":75,"height":26},"_trs":{"__type__":"TypedArray","ctor":"Float64Array","array":[-17.1,-46.1,0,0,0,0,1,1,1,1]},"_zIndex":0},{"__type__":"cc.Node","_name":"label","_parent":{"__id__":161},"_components":[{"__id__":163},{"__type__":"cc.LabelOutline","node":{"__id__":162},"_color":{"__type__":"cc.Color","r":39,"g":175,"b":49},"_width":1.5}],"_prefab":{"__type__":"cc.PrefabInfo","root":{"__id__":89},"asset":{"__uuid__":"0f8pKVU3ZK/pE1BlnxmB7s"},"fileId":"1ctiAFcyVIra/HIToQrrtf"},"_contentSize":{"__type__":"cc.Size","width":54,"height":20},"_trs":{"__type__":"TypedArray","ctor":"Float64Array","array":[0,1.2,0,0,0,0,1,1,1,1]},"_zIndex":0},{"__type__":"cc.Label","node":{"__id__":162},"_srcBlendFactor":1,"_useOriginalSize":false,"_string":"00:00:23","_N$string":"00:00:23","_fontSize":12,"_lineHeight":16,"_enableWrapText":false,"_N$horizontalAlign":1,"_N$verticalAlign":1,"_N$overflow":2},{"__type__":"cc.Node","_name":"common_frame_amount","_parent":{"__id__":160},"_children":[{"__id__":165}],"_components":[{"__type__":"cc.Sprite","node":{"__id__":164},"_spriteFrame":{"__uuid__":"c6eTEZj5BMNJNpHnILwXXo"},"_sizeMode":2,"_isTrimmedMode":false}],"_prefab":{"__type__":"cc.PrefabInfo","root":{"__id__":89},"asset":{"__uuid__":"0f8pKVU3ZK/pE1BlnxmB7s"},"fileId":"8e+N/elyhN4YLAUIxdT6wH"},"_contentSize":{"__type__":"cc.Size","width":66,"height":70},"_trs":{"__type__":"TypedArray","ctor":"Float64Array","array":[50,-40,0,0,0,0,1,0.75,0.75,1]},"_zIndex":0},{"__type__":"cc.Node","_name":"amountLabel","_parent":{"__id__":164},"_components":[{"__id__":166}],"_prefab":{"__type__":"cc.PrefabInfo","root":{"__id__":89},"asset":{"__uuid__":"0f8pKVU3ZK/pE1BlnxmB7s"},"fileId":"7aq7Dry61AFbXojHzYX5h8"},"_contentSize":{"__type__":"cc.Size","width":39.5,"height":23.63},"_trs":{"__type__":"TypedArray","ctor":"Float64Array","array":[0,3,0,0,0,0,1,1,1,1]},"_zIndex":0},{"__type__":"cc.Label","node":{"__id__":165},"_useOriginalSize":false,"_string":"99","_N$string":"99","_fontSize":36,"_lineHeight":21,"_N$file":{"__uuid__":"96/Cmi4OpC2IkOdTDlMLwZ"},"_isSystemFontUsed":false,"_spacingX":-1,"_N$horizontalAlign":1,"_N$verticalAlign":1},{"__type__":"cc.Node","_name":"lockIcon","_parent":{"__id__":145},"_components":[{"__type__":"cc.Sprite","node":{"__id__":167},"_spriteFrame":{"__uuid__":"9cFmNJcn1Hb5r5Y629iJ5M"}},{"__type__":"069c1FU/nxJ6YeuYJ8bTF9J","node":{"__id__":167},"limitTouchTime":500}],"_prefab":{"__type__":"cc.PrefabInfo","root":{"__id__":89},"asset":{"__uuid__":"0f8pKVU3ZK/pE1BlnxmB7s"},"fileId":"d5Hfw18DdLfoJlkzVGpgwn"},"_contentSize":{"__type__":"cc.Size","width":57,"height":74},"_trs":{"__type__":"TypedArray","ctor":"Float64Array","array":[0,0,0,0,0,0,1,1,1,1]},"_zIndex":0},{"__type__":"27f1ez202tMP7oxJ80RscXS","node":{"__id__":145}},{"__type__":"cc.Node","_name":"instructionLabelDown","_parent":{"__id__":92},"_components":[{"__id__":170}],"_prefab":{"__type__":"cc.PrefabInfo","root":{"__id__":89},"asset":{"__uuid__":"0f8pKVU3ZK/pE1BlnxmB7s"},"fileId":"e68kG+4QZIL5aQkcjoBJX4"},"_contentSize":{"__type__":"cc.Size","width":96,"height":30},"_trs":{"__type__":"TypedArray","ctor":"Float64Array","array":[0,142,0,0,0,0,1,1,1,1]},"_zIndex":0},{"__type__":"cc.Label","node":{"__id__":169},"_srcBlendFactor":1,"_useOriginalSize":false,"_string":"","_N$string":"","_fontSize":24,"_lineHeight":30,"_N$horizontalAlign":1,"_N$verticalAlign":1},{"__type__":"cc.Node","_name":"DrawButtonFrame","_parent":{"__id__":89},"_children":[{"__id__":172},{"__id__":173},{"__id__":174},{"__id__":177}],"_components":[{"__type__":"cc.Widget","node":{"__id__":171},"alignMode":0,"_alignFlags":44,"_bottom":250,"_originalWidth":720}],"_prefab":{"__type__":"cc.PrefabInfo","root":{"__id__":89},"asset":{"__uuid__":"0f8pKVU3ZK/pE1BlnxmB7s"},"fileId":"adiuyCQ8NCZ6tLblTWmTXq"},"_contentSize":{"__type__":"cc.Size","width":720,"height":35},"_trs":{"__type__":"TypedArray","ctor":"Float64Array","array":[0,-372.5,0,0,0,0,1,1,1,1]},"_zIndex":0},{"__type__":"cc.Node","_name":"match_draw_buttonkuosan1","_parent":{"__id__":171},"_components":[{"__type__":"cc.Sprite","node":{"__id__":172},"_spriteFrame":{"__uuid__":"edzj7t1kxEHqQFV+OCbioQ"}}],"_prefab":{"__type__":"cc.PrefabInfo","root":{"__id__":89},"asset":{"__uuid__":"0f8pKVU3ZK/pE1BlnxmB7s"},"fileId":"eeR4R9vJlJ+rNYLMkyy1HG"},"_opacity":0,"_contentSize":{"__type__":"cc.Size","width":122,"height":36},"_trs":{"__type__":"TypedArray","ctor":"Float64Array","array":[0,0,0,0,0,0,1,1,1,1]},"_zIndex":0},{"__type__":"cc.Node","_name":"match_draw_buttonkuosan2","_parent":{"__id__":171},"_components":[{"__type__":"cc.Sprite","node":{"__id__":173},"_spriteFrame":{"__uuid__":"edzj7t1kxEHqQFV+OCbioQ"}}],"_prefab":{"__type__":"cc.PrefabInfo","root":{"__id__":89},"asset":{"__uuid__":"0f8pKVU3ZK/pE1BlnxmB7s"},"fileId":"33mU7/0ndL7LlrL8yffDx2"},"_opacity":0,"_contentSize":{"__type__":"cc.Size","width":122,"height":36},"_trs":{"__type__":"TypedArray","ctor":"Float64Array","array":[0,0,0,0,0,0,1,1,1,1]},"_zIndex":0},{"__type__":"cc.Node","_name":"drawUpButton","_parent":{"__id__":171},"_children":[{"__id__":175},{"__id__":176}],"_components":[{"__type__":"cc.Sprite","node":{"__id__":174},"_spriteFrame":{"__uuid__":"49px9K7K1DMr3/EdT3q18h"}}],"_prefab":{"__type__":"cc.PrefabInfo","root":{"__id__":89},"asset":{"__uuid__":"0f8pKVU3ZK/pE1BlnxmB7s"},"fileId":"c22y1NNR5A/qB1xrhyHhLp"},"_contentSize":{"__type__":"cc.Size","width":122,"height":36},"_trs":{"__type__":"TypedArray","ctor":"Float64Array","array":[0,0,0,0,0,0,1,1,1,1]},"_zIndex":0},{"__type__":"cc.Node","_name":"match_draw_button_up","_parent":{"__id__":174},"_components":[{"__type__":"cc.Sprite","node":{"__id__":175},"_spriteFrame":{"__uuid__":"df/dhE2B1MJIPVkh8S79yc"}}],"_prefab":{"__type__":"cc.PrefabInfo","root":{"__id__":89},"asset":{"__uuid__":"0f8pKVU3ZK/pE1BlnxmB7s"},"fileId":"cf7MXLINVJ75aC+j+qA+bu"},"_contentSize":{"__type__":"cc.Size","width":29,"height":14},"_trs":{"__type__":"TypedArray","ctor":"Float64Array","array":[0,0,0,0,0,0,1,1,1,1]},"_zIndex":0},{"__type__":"cc.Node","_name":"match_draw_buttonbai","_parent":{"__id__":174},"_components":[{"__type__":"cc.Sprite","node":{"__id__":176},"_spriteFrame":{"__uuid__":"89PlAl95RPaZyr7SLdcre5"}}],"_prefab":{"__type__":"cc.PrefabInfo","root":{"__id__":89},"asset":{"__uuid__":"0f8pKVU3ZK/pE1BlnxmB7s"},"fileId":"3ckIEF8nNKAJqJU1WrYzFy"},"_opacity":0,"_contentSize":{"__type__":"cc.Size","width":122,"height":36},"_trs":{"__type__":"TypedArray","ctor":"Float64Array","array":[0,0,0,0,0,0,1,1,1,1]},"_zIndex":0},{"__type__":"cc.Node","_name":"instructionLabelUp","_parent":{"__id__":171},"_components":[{"__id__":178}],"_prefab":{"__type__":"cc.PrefabInfo","root":{"__id__":89},"asset":{"__uuid__":"0f8pKVU3ZK/pE1BlnxmB7s"},"fileId":"19qZ//6DlN6JWDhfhXVUQc"},"_contentSize":{"__type__":"cc.Size","width":96,"height":30},"_trs":{"__type__":"TypedArray","ctor":"Float64Array","array":[0,37,0,0,0,0,1,1,1,1]},"_zIndex":0},{"__type__":"cc.Label","node":{"__id__":177},"_srcBlendFactor":1,"_useOriginalSize":false,"_string":"","_N$string":"","_fontSize":24,"_lineHeight":30,"_N$horizontalAlign":1,"_N$verticalAlign":1},{"__type__":"cc.Node","_name":"pullUpCover","_parent":{"__id__":89},"_components":[{"__type__":"cc.Sprite","node":{"__id__":179},"_spriteFrame":{"__uuid__":"a2MjXRFdtLlYQ5ouAFv/+R"},"_sizeMode":0},{"__type__":"cc.Widget","node":{"__id__":179},"alignMode":0,"_alignFlags":1,"_top":1280}],"_prefab":{"__type__":"cc.PrefabInfo","root":{"__id__":89},"asset":{"__uuid__":"0f8pKVU3ZK/pE1BlnxmB7s"},"fileId":"ce8Mk/RBlGD7N9RZq1DBWa"},"_color":{"__type__":"cc.Color"},"_contentSize":{"__type__":"cc.Size","width":720,"height":100},"_anchorPoint":{"__type__":"cc.Vec2","x":0.5,"y":1},"_trs":{"__type__":"TypedArray","ctor":"Float64Array","array":[0,-640,0,0,0,0,1,1,1,1]},"_zIndex":0},{"__type__":"8ebb9IAwohLDYC/Q3f+EDKs","node":{"__id__":89},"itemsNode":[{"__id__":97},{"__id__":121},{"__id__":145}],"instroductionLabelDown":{"__id__":170},"drawUpButton":{"__id__":174},"drawUpButtonFrame":{"__id__":171},"instroductionLabelUp":{"__id__":178},"fallDownButton":{"__id__":93},"fallDownLayer":{"__id__":90},"GearBarRoot":{"__id__":92},"pullUpCover":{"__id__":179}},{"__type__":"cc.Node","_name":"swallowTouchLayer","_parent":{"__id__":2},"_components":[{"__type__":"cc.BlockInputEvents","node":{"__id__":181}},{"__type__":"cc.Widget","node":{"__id__":181},"alignMode":0,"_alignFlags":45}],"_contentSize":{"__type__":"cc.Size","width":720,"height":1280},"_trs":{"__type__":"TypedArray","ctor":"Float64Array","array":[0,0,0,0,0,0,1,1,1,1]},"_zIndex":0}]