{"__type__":"cc.JsonAsset","_name":"CFGTripleMap1010046","json":{"MapId":"1010046","MapData":"{\"height\":9,\"infinite\":false,\"layers\":[{\"data\":[0,0,0,1,1,1,0,0,0,0,0,1,1,1,1,1,0,0,0,1,1,1,1,1,1,1,0,1,1,1,1,1,1,1,1,1,1,1,1,1,1,1,1,1,1,1,1,1,1,1,1,1,1,1,1,1,1,1,1,1,1,1,1,1,1,1,1,1,1,1,1,1,0,1,1,1,1,1,1,1,0],\"height\":9,\"name\":\"Cells\",\"opacity\":1,\"type\":\"tilelayer\",\"visible\":true,\"width\":9,\"x\":0,\"y\":0},{\"draworder\":\"topdown\",\"name\":\"Cells\",\"objects\":[],\"opacity\":1,\"properties\":{\"dropType\":\"default\"},\"propertytypes\":{\"dropType\":\"string\"},\"type\":\"objectgroup\",\"visible\":true,\"x\":0,\"y\":0},{\"data\":[0,0,0,0,0,0,0,0,0,0,0,0,0,0,0,0,0,0,0,0,0,0,0,0,0,0,0,0,0,0,0,0,0,0,0,0,0,0,0,0,0,0,0,0,0,0,0,0,0,0,0,0,0,0,0,0,0,0,0,0,0,0,0,0,0,0,0,0,0,0,0,0,0,0,0,0,0,0,0,0,0],\"height\":9,\"name\":\"Conveyers\",\"opacity\":1,\"type\":\"tilelayer\",\"visible\":true,\"width\":9,\"x\":0,\"y\":0},{\"draworder\":\"topdown\",\"name\":\"Conveyers\",\"objects\":[],\"opacity\":1,\"type\":\"objectgroup\",\"visible\":true,\"x\":0,\"y\":0},{\"data\":[0,0,0,0,0,0,0,0,0,0,0,0,0,0,0,0,0,0,0,0,0,0,0,0,0,0,0,0,0,0,0,0,0,0,0,0,0,0,0,0,0,0,0,0,0,0,0,0,0,0,0,0,0,0,0,0,0,0,0,0,0,0,0,0,0,0,0,0,0,0,0,0,0,0,0,0,0,0,0,0,0],\"height\":9,\"name\":\"Floors\",\"opacity\":1,\"type\":\"tilelayer\",\"visible\":true,\"width\":9,\"x\":0,\"y\":0},{\"data\":[0,0,0,0,0,0,0,0,0,0,0,0,0,0,0,0,0,0,0,0,0,0,0,0,0,0,0,0,0,0,0,0,0,0,0,0,0,0,0,0,0,0,0,0,0,0,0,0,0,0,0,0,0,0,0,0,0,0,0,0,0,0,0,0,0,0,0,0,0,0,0,0,0,0,0,0,0,0,0,0,0],\"height\":9,\"name\":\"Jam\",\"opacity\":1,\"type\":\"tilelayer\",\"visible\":true,\"width\":9,\"x\":0,\"y\":0},{\"data\":[0,0,0,182,182,182,0,0,0,0,0,182,182,182,182,182,0,0,0,143,182,182,182,182,182,143,0,137,143,182,182,182,182,182,143,137,137,143,182,182,182,182,182,143,137,137,143,182,182,182,182,182,143,137,137,143,182,182,182,182,182,143,137,137,143,182,182,182,182,182,143,137,0,143,182,182,182,182,182,143,0],\"height\":9,\"name\":\"Items\",\"opacity\":1,\"type\":\"tilelayer\",\"visible\":true,\"width\":9,\"x\":0,\"y\":0},{\"draworder\":\"topdown\",\"name\":\"Items\",\"objects\":[{\"height\":0,\"id\":410,\"name\":\"\",\"properties\":{\"max\":\"5\"},\"propertytypes\":{\"max\":\"string\"},\"rotation\":0,\"type\":\"\",\"visible\":true,\"width\":0,\"x\":850,\"y\":550},{\"height\":0,\"id\":443,\"name\":\"\",\"properties\":{\"max\":\"5\"},\"propertytypes\":{\"max\":\"string\"},\"rotation\":0,\"type\":\"\",\"visible\":true,\"width\":0,\"x\":50,\"y\":550},{\"height\":0,\"id\":444,\"name\":\"\",\"properties\":{\"max\":\"3\"},\"propertytypes\":{\"max\":\"string\"},\"rotation\":0,\"type\":\"\",\"visible\":true,\"width\":0,\"x\":50,\"y\":450},{\"height\":0,\"id\":445,\"name\":\"\",\"properties\":{\"max\":\"2\"},\"propertytypes\":{\"max\":\"string\"},\"rotation\":0,\"type\":\"\",\"visible\":true,\"width\":0,\"x\":50,\"y\":350},{\"height\":0,\"id\":446,\"name\":\"\",\"properties\":{\"max\":\"3\"},\"propertytypes\":{\"max\":\"string\"},\"rotation\":0,\"type\":\"\",\"visible\":true,\"width\":0,\"x\":50,\"y\":650},{\"height\":0,\"id\":447,\"name\":\"\",\"properties\":{\"max\":\"2\"},\"propertytypes\":{\"max\":\"string\"},\"rotation\":0,\"type\":\"\",\"visible\":true,\"width\":0,\"x\":50,\"y\":750},{\"height\":0,\"id\":448,\"name\":\"\",\"properties\":{\"max\":\"2\"},\"propertytypes\":{\"max\":\"string\"},\"rotation\":0,\"type\":\"\",\"visible\":true,\"width\":0,\"x\":850,\"y\":350},{\"height\":0,\"id\":449,\"name\":\"\",\"properties\":{\"max\":\"3\"},\"propertytypes\":{\"max\":\"string\"},\"rotation\":0,\"type\":\"\",\"visible\":true,\"width\":0,\"x\":850,\"y\":450},{\"height\":0,\"id\":450,\"name\":\"\",\"properties\":{\"max\":\"3\"},\"propertytypes\":{\"max\":\"string\"},\"rotation\":0,\"type\":\"\",\"visible\":true,\"width\":0,\"x\":850,\"y\":650},{\"height\":0,\"id\":451,\"name\":\"\",\"properties\":{\"max\":\"2\"},\"propertytypes\":{\"max\":\"string\"},\"rotation\":0,\"type\":\"\",\"visible\":true,\"width\":0,\"x\":850,\"y\":750}],\"opacity\":1,\"type\":\"objectgroup\",\"visible\":true,\"x\":0,\"y\":0},{\"data\":[0,0,0,0,0,0,0,0,0,0,0,235,0,0,0,235,0,0,0,0,235,0,0,0,235,0,0,0,0,235,0,0,0,235,0,0,0,0,235,0,0,0,235,0,0,0,0,235,0,0,0,235,0,0,0,0,235,0,0,0,235,0,0,0,0,235,0,0,0,235,0,0,0,0,235,0,0,0,235,0,0],\"height\":9,\"name\":\"Parasites\",\"opacity\":1,\"type\":\"tilelayer\",\"visible\":true,\"width\":9,\"x\":0,\"y\":0},{\"data\":[0,0,0,0,0,0,0,0,0,0,0,0,0,0,0,0,0,0,0,0,0,0,0,0,0,0,0,0,0,0,0,0,0,0,0,0,0,0,0,0,0,0,0,0,0,0,0,0,0,0,0,0,0,0,0,0,0,0,0,0,0,0,0,0,0,0,0,0,0,0,0,0,0,0,0,0,0,0,0,0,0],\"height\":9,\"name\":\"Marks\",\"opacity\":1,\"type\":\"tilelayer\",\"visible\":true,\"width\":9,\"x\":0,\"y\":0},{\"draworder\":\"topdown\",\"name\":\"Marks\",\"objects\":[{\"gid\":220,\"height\":100,\"id\":429,\"name\":\"\",\"rotation\":0,\"type\":\"\",\"visible\":true,\"width\":100,\"x\":150,\"y\":300},{\"gid\":220,\"height\":100,\"id\":430,\"name\":\"\",\"rotation\":0,\"type\":\"\",\"visible\":true,\"width\":100,\"x\":150,\"y\":400},{\"gid\":220,\"height\":100,\"id\":431,\"name\":\"\",\"rotation\":0,\"type\":\"\",\"visible\":true,\"width\":100,\"x\":150,\"y\":500},{\"gid\":220,\"height\":100,\"id\":432,\"name\":\"\",\"rotation\":0,\"type\":\"\",\"visible\":true,\"width\":100,\"x\":150,\"y\":600},{\"gid\":220,\"height\":100,\"id\":433,\"name\":\"\",\"rotation\":0,\"type\":\"\",\"visible\":true,\"width\":100,\"x\":150,\"y\":700},{\"gid\":220,\"height\":100,\"id\":434,\"name\":\"\",\"rotation\":0,\"type\":\"\",\"visible\":true,\"width\":100,\"x\":150,\"y\":800},{\"gid\":220,\"height\":100,\"id\":435,\"name\":\"\",\"rotation\":0,\"type\":\"\",\"visible\":true,\"width\":100,\"x\":150,\"y\":900},{\"gid\":220,\"height\":100,\"id\":436,\"name\":\"\",\"rotation\":0,\"type\":\"\",\"visible\":true,\"width\":100,\"x\":650,\"y\":300},{\"gid\":220,\"height\":100,\"id\":437,\"name\":\"\",\"rotation\":0,\"type\":\"\",\"visible\":true,\"width\":100,\"x\":650,\"y\":400},{\"gid\":220,\"height\":100,\"id\":438,\"name\":\"\",\"rotation\":0,\"type\":\"\",\"visible\":true,\"width\":100,\"x\":650,\"y\":500},{\"gid\":220,\"height\":100,\"id\":439,\"name\":\"\",\"rotation\":0,\"type\":\"\",\"visible\":true,\"width\":100,\"x\":650,\"y\":600},{\"gid\":220,\"height\":100,\"id\":440,\"name\":\"\",\"rotation\":0,\"type\":\"\",\"visible\":true,\"width\":100,\"x\":650,\"y\":700},{\"gid\":220,\"height\":100,\"id\":441,\"name\":\"\",\"rotation\":0,\"type\":\"\",\"visible\":true,\"width\":100,\"x\":650,\"y\":800},{\"gid\":220,\"height\":100,\"id\":442,\"name\":\"\",\"rotation\":0,\"type\":\"\",\"visible\":true,\"width\":100,\"x\":650,\"y\":900}],\"opacity\":1,\"type\":\"objectgroup\",\"visible\":true,\"x\":0,\"y\":0}],\"nextobjectid\":452,\"orientation\":\"orthogonal\",\"renderorder\":\"left-up\",\"tiledversion\":\"1.1.4\",\"tileheight\":100,\"tilesets\":[{\"firstgid\":1,\"source\":\"../TiledMaps/Cells.json\"},{\"firstgid\":25,\"source\":\"../TiledMaps/Conveyers.json\"},{\"firstgid\":49,\"source\":\"../TiledMaps/Floors.json\"},{\"firstgid\":85,\"source\":\"../TiledMaps/Items.json\"},{\"firstgid\":205,\"source\":\"../TiledMaps/Jam.json\"},{\"firstgid\":217,\"source\":\"../TiledMaps/Marks.json\"},{\"firstgid\":229,\"source\":\"../TiledMaps/Parasite.json\"}],\"tilewidth\":100,\"type\":\"map\",\"version\":1,\"width\":9}"}}